{"profile":"vu_thu","web_app":"https://bao-cao-vu-thu.vercel.app/","cap_nhat_luc":"15/06/2026 17:31:56","tong_so_kh":185,"du_lieu":[{"Mã Sổ GCS":"0204A","ID hóa đơn":1779859335.0,"Mã khách hàng":"PA09020323509","Tên khách hàng":"CÔNG TY TNHH CREATIVE SOURCE VIỆT NAM","Địa chỉ khách hàng":"Lô CN 2 và CN3, DT 71.744,3m2 , cụm Công nghiệp Minh Lãng, xã Thư Trì, tỉnh Hưng Yên, Việt Nam","Kỳ-tháng/năm":"1-6/2026","Loại hóa đơn":"TD","Ngày phát hành":"10-06-2026 00:00:00","Tổng tiền":"739.563.728","Số điện thoại":977181082.0,"Thu ngân viên":"CHUYÊN DÙNG","Số CTơ":2046013471.0,"Số Cột":1,"Tên Trạm":"CÔNG TY TNHH CREATIVE SOURCE VIỆT NAM"},{"Mã Sổ GCS":"0204A","ID hóa đơn":1779859325.0,"Mã khách hàng":"PA09020323883","Tên khách hàng":"Công ty TNHH Dệt nhuộm xuất khẩu Thăng Long","Địa chỉ khách hàng":"Lô A1 KCN Nguyễn Đức Cảnh,  Phường Trần Hưng Đạo,tỉnh Hưng Yên, Việt Nam","Kỳ-tháng/năm":"1-6/2026","Loại hóa đơn":"TD","Ngày phát hành":"10-06-2026 00:00:00","Tổng tiền":"2.148.659.758","Số điện thoại":886731999.0,"Thu ngân viên":"CHUYÊN DÙNG","Số CTơ":2046013217.0,"Số Cột":1,"Tên Trạm":"CÔNG TY TNHH DỆT NHUỘM XUẤT KHẨU THĂNG LONG(T4)"},{"Mã Sổ GCS":"0204A","ID hóa đơn":1779859329.0,"Mã khách hàng":"PA09020323282","Tên khách hàng":"CÔNG TY TNHH LEADER WIN SHOES","Địa chỉ khách hàng":"Nhà ông Sơn, Thôn Dũng Thượng, Xã Vũ Thư, tỉnh Hưng Yên, Việt Nam","Kỳ-tháng/năm":"1-6/2026","Loại hóa đơn":"TD","Ngày phát hành":"10-06-2026 00:00:00","Tổng tiền":"203.301.101","Số điện thoại":829311111.0,"Thu ngân viên":"CHUYÊN DÙNG","Số CTơ":2046013452.0,"Số Cột":1,"Tên Trạm":"CÔNG TY TNHH SẢN XUẤT DỊCH VỤ THƯƠNG MẠI SƠN NGỌC ĐỨC VIỆT"},{"Mã Sổ GCS":"0204A","ID hóa đơn":1779859333.0,"Mã khách hàng":"PA09020323851","Tên khách hàng":"CÔNG TY TNHH VẬT LIỆU GIÀY LUDEN VIỆT NAM","Địa chỉ khách hàng":"Lô B, cụm Công nghiệp Vũ Thư Xã Vũ Thư, Tỉnh Hưng Yên, Việt Nam","Kỳ-tháng/năm":"1-6/2026","Loại hóa đơn":"TD","Ngày phát hành":"10-06-2026 00:00:00","Tổng tiền":"202.674.096","Số điện thoại":336692177.0,"Thu ngân viên":"CHUYÊN DÙNG","Số CTơ":2510779307.0,"Số Cột":1,"Tên Trạm":"CÔNG TY CỔ PHẦN THƯƠNG MẠI BÔNG SỢI HOÀNG TUẤN"},{"Mã Sổ GCS":"0204A","ID hóa đơn":1779859319.0,"Mã khách hàng":"PA09020330850","Tên khách hàng":"Công ty TNHH giày VICTORY Việt Nam","Địa chỉ khách hàng":"Lô C, Lô D ,Cụm công nghiệp, xã Vũ Thư, tỉnh Hưng Yên, Việt Nam","Kỳ-tháng/năm":"1-6/2026","Loại hóa đơn":"TD","Ngày phát hành":"10-06-2026 00:00:00","Tổng tiền":"514.274.519","Số điện thoại":913145080.0,"Thu ngân viên":"CHUYÊN DÙNG","Số CTơ":2046014202.0,"Số Cột":1,"Tên Trạm":"CÔNG TY TNHH GIẦY VICTORY VIỆT NAM"},{"Mã Sổ GCS":"0204A","ID hóa đơn":1779859337.0,"Mã khách hàng":"PA09020308593","Tên khách hàng":"Công ty trách nhiệm hữu hạn Liên Hạnh","Địa chỉ khách hàng":"Lô B, diện tích 28.055m2,Cụm công nghiệp, xã Vũ Thư, tỉnh Hưng Yên","Kỳ-tháng/năm":"1-6/2026","Loại hóa đơn":"TD","Ngày phát hành":"10-06-2026 00:00:00","Tổng tiền":"174.496.356","Số điện thoại":914211856.0,"Thu ngân viên":"CHUYÊN DÙNG","Số CTơ":2046013165.0,"Số Cột":1,"Tên Trạm":"Công  Ty TNHH Liên Hạnh(T2)"},{"Mã Sổ GCS":"0204A","ID hóa đơn":1779859339.0,"Mã khách hàng":"PA09020334767","Tên khách hàng":"Công ty TNHH Xuất nhập khẩu COYATO","Địa chỉ khách hàng":"Cụm Công Nghiệp Tân Minh,  Xã Vũ Thư, Tỉnh Hưng Yên, Việt Nam","Kỳ-tháng/năm":"1-6/2026","Loại hóa đơn":"TD","Ngày phát hành":"10-06-2026 00:00:00","Tổng tiền":"281.658.807","Số điện thoại":902167880.0,"Thu ngân viên":"CHUYÊN DÙNG","Số CTơ":20460407.0,"Số Cột":1,"Tên Trạm":"Công ty TNHH xuất nhập khẩu COYATO"},{"Mã Sổ GCS":"0204A","ID hóa đơn":1779859341.0,"Mã khách hàng":"PA09020337903","Tên khách hàng":"Công ty cổ phần Quốc tế Phú Quý Packaging","Địa chỉ khách hàng":"Khu CN1, cụm công nghiệp Tân Minh, xã Vũ Thư, tỉnh Hưng Yên, Việt Nam","Kỳ-tháng/năm":"1-6/2026","Loại hóa đơn":"TD","Ngày phát hành":"10-06-2026 00:00:00","Tổng tiền":"151.814.520","Số điện thoại":985894568.0,"Thu ngân viên":"CHUYÊN DÙNG","Số CTơ":20460606.0,"Số Cột":13,"Tên Trạm":"Công ty cổ phần Quốc tế Phú Quý PACKAGING(T1)"},{"Mã Sổ GCS":"0204A","ID hóa đơn":1779859321.0,"Mã khách hàng":"PA09020339433","Tên khách hàng":"CÔNG TY TNHH CÔNG NGHIỆP YINRUN (VIỆT NAM)","Địa chỉ khách hàng":"Lô CN4, Cụm Công Nghiệp Minh Lãng, xã Thư Trì, Tỉnh Hưng Yên, Việt Nam","Kỳ-tháng/năm":"1-6/2026","Loại hóa đơn":"TD","Ngày phát hành":"10-06-2026 00:00:00","Tổng tiền":"101.870.352","Số điện thoại":985962777.0,"Thu ngân viên":"CHUYÊN DÙNG","Số CTơ":2346011520.0,"Số Cột":1,"Tên Trạm":"Công ty cổ phần Minh Phát Plastic"},{"Mã Sổ GCS":"0204A","ID hóa đơn":1779859331.0,"Mã khách hàng":"PA09020349485","Tên khách hàng":"Công ty TNHH Super Victory Thái Bình","Địa chỉ khách hàng":"Lô CN2, Cụm công nghiệp Tân Minh, Xã Tân Thuận, Tỉnh Hưng Yên, Việt Nam","Kỳ-tháng/năm":"1-6/2026","Loại hóa đơn":"TD","Ngày phát hành":"10-06-2026 00:00:00","Tổng tiền":"172.232.762","Số điện thoại":982924628.0,"Thu ngân viên":"CHUYÊN DÙNG","Số CTơ":2411291186.0,"Số Cột":19,"Tên Trạm":"Công ty TNHH Super Victory Thái Bình(T1)"},{"Mã Sổ GCS":"0204A","ID hóa đơn":1779859327.0,"Mã khách hàng":"PA09020349554","Tên khách hàng":"CÔNG TY TNHH CÔNG NGHỆ MAY MẶC SPECTRE VIỆT NAM","Địa chỉ khách hàng":"Lô O1, đường N5A, Khu công nghiệp Hòa Xá,  Phường Thành Nam, Tỉnh Ninh Bình, Việt Nam","Kỳ-tháng/năm":"1-6/2026","Loại hóa đơn":"TD","Ngày phát hành":"10-06-2026 00:00:00","Tổng tiền":"109.229.900","Số điện thoại":985265492.0,"Thu ngân viên":"CHUYÊN DÙNG","Số CTơ":2411291114.0,"Số Cột":1,"Tên Trạm":"Công ty TNHH may Việt Tiến Thái Bình"},{"Mã Sổ GCS":"0204A","ID hóa đơn":1779859347.0,"Mã khách hàng":"PA09020349582","Tên khách hàng":"Công ty cổ phần quốc tế Phú Quý Packaging","Địa chỉ khách hàng":"Khu CN 1, cụm công nghiệp Tân Minh, Xã Vũ thư, Tỉnh Hưng Yên, Việt Nam\t","Kỳ-tháng/năm":"1-6/2026","Loại hóa đơn":"TD","Ngày phát hành":"10-06-2026 00:00:00","Tổng tiền":"113.414.688","Số điện thoại":353111276.0,"Thu ngân viên":"CHUYÊN DÙNG","Số CTơ":2411291144.0,"Số Cột":1,"Tên Trạm":"Công ty cổ phần Quốc tế Phú Quý PACKAGING(T2)"},{"Mã Sổ GCS":"0204B","ID hóa đơn":1779859317.0,"Mã khách hàng":"PA09020200361","Tên khách hàng":"Công ty cổ phần Gốm xây dựng Đại Thắng","Địa chỉ khách hàng":"Lô đất diện tích 77.760,7m2 thôn Nẽ Châu, Xã Vũ Thư, Tỉnh Hưng Yên, Việt Nam","Kỳ-tháng/năm":"1-6/2026","Loại hóa đơn":"TD","Ngày phát hành":"10-06-2026 00:00:00","Tổng tiền":"141.525.680","Số điện thoại":913361678.0,"Thu ngân viên":"CHUYÊN DÙNG","Số CTơ":2411290852.0,"Số Cột":1,"Tên Trạm":"Công ty cổ phần xây dựng gốm Đại Thắng"},{"Mã Sổ GCS":"0204B","ID hóa đơn":1779859315.0,"Mã khách hàng":"PA09020200504","Tên khách hàng":"CÔNG TY TRÁCH NHIỆM HỮU HẠN IVORY VIỆT NAM","Địa chỉ khách hàng":"Km 6+ 500, quốc lộ 10, Xã Vũ Thư, Tỉnh Hưng Yên, Việt Nam","Kỳ-tháng/năm":"1-6/2026","Loại hóa đơn":"TD","Ngày phát hành":"10-06-2026 00:00:00","Tổng tiền":"221.422.240","Số điện thoại":983527069.0,"Thu ngân viên":"CHUYÊN DÙNG","Số CTơ":2046013370.0,"Số Cột":1,"Tên Trạm":"Trạm IVORY - T1"},{"Mã Sổ GCS":"0204D","ID hóa đơn":1779859309.0,"Mã khách hàng":"PA09020349399","Tên khách hàng":"CÔNG TY TNHH JEIL JERSEY VINA","Địa chỉ khách hàng":"Lô đất diện tích 24.433,5 m2,cụm công nghiệp Vũ Hội, Xã Thư Vũ, Tỉnh Hưng Yên, Việt Nam","Kỳ-tháng/năm":"1-6/2026","Loại hóa đơn":"TD","Ngày phát hành":"10-06-2026 00:00:00","Tổng tiền":"135.702.968","Số điện thoại":989045632.0,"Thu ngân viên":"CHUYÊN DÙNG","Số CTơ":2411291101.0,"Số Cột":1,"Tên Trạm":"CTy TNHH JEIL JERSEY VINA"},{"Mã Sổ GCS":"","ID hóa đơn":"","Mã khách hàng":"","Tên khách hàng":"","Địa chỉ khách hàng":"","Kỳ-tháng/năm":"Số hóa đơn: 15 HĐ","Loại hóa đơn":"","Ngày phát hành":"","Tổng tiền":"5.411.841.475","Số điện thoại":"","Thu ngân viên":"","Số CTơ":"","Số Cột":"","Tên Trạm":""},{"Mã Sổ GCS":"","ID hóa đơn":"","Mã khách hàng":"","Tên khách hàng":"Thu ngân viên","Địa chỉ khách hàng":"","Kỳ-tháng/năm":"","Loại hóa đơn":"Kế toán","Ngày phát hành":"","Tổng tiền":"0","Số điện thoại":"","Thu ngân viên":"Phòng kinh doanh","Số CTơ":"","Số Cột":"","Tên Trạm":""},{"Mã Sổ GCS":"","ID hóa đơn":"","Mã khách hàng":"","Tên khách hàng":"(Ký, họ tên)","Địa chỉ khách hàng":"","Kỳ-tháng/năm":"","Loại hóa đơn":"(Ký, họ tên)","Ngày phát hành":"","Tổng tiền":"0","Số điện thoại":"","Thu ngân viên":"(Ký, họ tên)","Số CTơ":"","Số Cột":"","Tên Trạm":""},{"Mã Sổ GCS":2737,"ID hóa đơn":1777364220.0,"Mã khách hàng":"PA09020346912","Tên khách hàng":"Vũ Văn Thi","Địa chỉ khách hàng":"Thôn Năng Tĩnh, Xã Thư Vũ, Tỉnh Hưng Yên","Kỳ-tháng/năm":"1-5/2026","Loại hóa đơn":"TD","Ngày phát hành":"02-06-2026 00:00:00","Tổng tiền":"10.714","Số điện thoại":388760190.0,"Thu ngân viên":"Thu Vũ Hội","Số CTơ":2210721335.0,"Số Cột":"2.2/1.1/1.1","Tên Trạm":"Vũ Hội 7"},{"Mã Sổ GCS":2742,"ID hóa đơn":1777363682.0,"Mã khách hàng":"PA09020347903","Tên khách hàng":"Đoàn Thị Mừng","Địa chỉ khách hàng":"Thôn Mỹ Am, Xã Thư Vũ, Tỉnh Hưng Yên","Kỳ-tháng/năm":"1-5/2026","Loại hóa đơn":"TD","Ngày phát hành":"02-06-2026 00:00:00","Tổng tiền":"597.914","Số điện thoại":387115311.0,"Thu ngân viên":"Thu Vũ Hội","Số CTơ":2110785899.0,"Số Cột":"1.8/1.2","Tên Trạm":"Vũ Hội 12"},{"Mã Sổ GCS":"","ID hóa đơn":"","Mã khách hàng":"","Tên khách hàng":"","Địa chỉ khách hàng":"","Kỳ-tháng/năm":"Số hóa đơn: 2 HĐ","Loại hóa đơn":"","Ngày phát hành":"","Tổng tiền":"608.628","Số điện thoại":"","Thu ngân viên":"","Số CTơ":"","Số Cột":"","Tên Trạm":""},{"Mã Sổ GCS":"","ID hóa đơn":"","Mã khách hàng":"","Tên khách hàng":"Thu ngân viên","Địa chỉ khách hàng":"","Kỳ-tháng/năm":"","Loại hóa đơn":"Kế toán","Ngày phát hành":"","Tổng tiền":"0","Số điện thoại":"","Thu ngân viên":"Phòng kinh doanh","Số CTơ":"","Số Cột":"","Tên Trạm":""},{"Mã Sổ GCS":"","ID hóa đơn":"","Mã khách hàng":"","Tên khách hàng":"(Ký, họ tên)","Địa chỉ khách hàng":"","Kỳ-tháng/năm":"","Loại hóa đơn":"(Ký, họ tên)","Ngày phát hành":"","Tổng tiền":"0","Số điện thoại":"","Thu ngân viên":"(Ký, họ tên)","Số CTơ":"","Số Cột":"","Tên Trạm":""},{"Mã Sổ GCS":"","ID hóa đơn":"","Mã khách hàng":"","Tên khách hàng":"","Địa chỉ khách hàng":"","Kỳ-tháng/năm":"Số hóa đơn: 0 HĐ","Loại hóa đơn":"","Ngày phát hành":"","Tổng tiền":"0","Số điện thoại":"","Thu ngân viên":"","Số CTơ":"","Số Cột":"","Tên Trạm":""},{"Mã Sổ GCS":"","ID hóa đơn":"","Mã khách hàng":"","Tên khách hàng":"Thu ngân viên","Địa chỉ khách hàng":"","Kỳ-tháng/năm":"","Loại hóa đơn":"Kế toán","Ngày phát hành":"","Tổng tiền":"0","Số điện thoại":"","Thu ngân viên":"Phòng kinh doanh","Số CTơ":"","Số Cột":"","Tên Trạm":""},{"Mã Sổ GCS":"","ID hóa đơn":"","Mã khách hàng":"","Tên khách hàng":"(Ký, họ tên)","Địa chỉ khách hàng":"","Kỳ-tháng/năm":"","Loại hóa đơn":"(Ký, họ tên)","Ngày phát hành":"","Tổng tiền":"0","Số điện thoại":"","Thu ngân viên":"(Ký, họ tên)","Số CTơ":"","Số Cột":"","Tên Trạm":""},{"Mã Sổ GCS":"","ID hóa đơn":"","Mã khách hàng":"","Tên khách hàng":"","Địa chỉ khách hàng":"","Kỳ-tháng/năm":"Số hóa đơn: 0 HĐ","Loại hóa đơn":"","Ngày phát hành":"","Tổng tiền":"0","Số điện thoại":"","Thu ngân viên":"","Số CTơ":"","Số Cột":"","Tên Trạm":""},{"Mã Sổ GCS":"","ID hóa đơn":"","Mã khách hàng":"","Tên khách hàng":"Thu ngân viên","Địa chỉ khách hàng":"","Kỳ-tháng/năm":"","Loại hóa đơn":"Kế toán","Ngày phát hành":"","Tổng tiền":"0","Số điện thoại":"","Thu ngân viên":"Phòng kinh doanh","Số CTơ":"","Số Cột":"","Tên Trạm":""},{"Mã Sổ GCS":"","ID hóa đơn":"","Mã khách hàng":"","Tên khách hàng":"(Ký, họ tên)","Địa chỉ khách hàng":"","Kỳ-tháng/năm":"","Loại hóa đơn":"(Ký, họ tên)","Ngày phát hành":"","Tổng tiền":"0","Số điện thoại":"","Thu ngân viên":"(Ký, họ tên)","Số CTơ":"","Số Cột":"","Tên Trạm":""},{"Mã Sổ GCS":2172,"ID hóa đơn":1777231373.0,"Mã khách hàng":"PA09020200001","Tên khách hàng":"CTTNHH Một thành viên KTCT thủy lợi Nam Thái Bình","Địa chỉ khách hàng":"Km3, phố Quang Trung,  phường Trần Hưng Đạo, tỉnh Hưng Yên, Việt Nam","Kỳ-tháng/năm":"1-5/2026","Loại hóa đơn":"TD","Ngày phát hành":"02-06-2026 00:00:00","Tổng tiền":"6.010.980","Số điện thoại":372937559.0,"Thu ngân viên":"Bơm thủy nông","Số CTơ":2046013425.0,"Số Cột":1,"Tên Trạm":"TBA B ơm Cự Lâm Xuân Hoà"},{"Mã Sổ GCS":2234,"ID hóa đơn":1776545149.0,"Mã khách hàng":"PA09020200001","Tên khách hàng":"CTTNHH Một thành viên KTCT thủy lợi Nam Thái Bình","Địa chỉ khách hàng":"Km3, phố Quang Trung,  phường Trần Hưng Đạo, tỉnh Hưng Yên, Việt Nam","Kỳ-tháng/năm":"1-5/2026","Loại hóa đơn":"TD","Ngày phát hành":"02-06-2026 00:00:00","Tổng tiền":"17.168","Số điện thoại":372937559.0,"Thu ngân viên":"Bơm thủy nông","Số CTơ":2110351895.0,"Số Cột":1,"Tên Trạm":"TBA B ơm Cự Lâm Xuân Hoà"},{"Mã Sổ GCS":2235,"ID hóa đơn":1776546692.0,"Mã khách hàng":"PA09020200001","Tên khách hàng":"CTTNHH Một thành viên KTCT thủy lợi Nam Thái Bình","Địa chỉ khách hàng":"Km3, phố Quang Trung,  phường Trần Hưng Đạo, tỉnh Hưng Yên, Việt Nam","Kỳ-tháng/năm":"1-5/2026","Loại hóa đơn":"TD","Ngày phát hành":"02-06-2026 00:00:00","Tổng tiền":"2.146","Số điện thoại":372937559.0,"Thu ngân viên":"Bơm thủy nông","Số CTơ":2110353113.0,"Số Cột":1,"Tên Trạm":"TBA B ơm Cự Lâm Xuân Hoà"},{"Mã Sổ GCS":2236,"ID hóa đơn":1776550438.0,"Mã khách hàng":"PA09020200001","Tên khách hàng":"CTTNHH Một thành viên KTCT thủy lợi Nam Thái Bình","Địa chỉ khách hàng":"Km3, phố Quang Trung,  phường Trần Hưng Đạo, tỉnh Hưng Yên, Việt Nam","Kỳ-tháng/năm":"1-5/2026","Loại hóa đơn":"TD","Ngày phát hành":"02-06-2026 00:00:00","Tổng tiền":"23.606","Số điện thoại":372937559.0,"Thu ngân viên":"Bơm thủy nông","Số CTơ":21279422.0,"Số Cột":1,"Tên Trạm":"TBA B ơm Cự Lâm Xuân Hoà"},{"Mã Sổ GCS":2237,"ID hóa đơn":1776548352.0,"Mã khách hàng":"PA09020200001","Tên khách hàng":"CTTNHH Một thành viên KTCT thủy lợi Nam Thái Bình","Địa chỉ khách hàng":"Km3, phố Quang Trung,  phường Trần Hưng Đạo, tỉnh Hưng Yên, Việt Nam","Kỳ-tháng/năm":"1-5/2026","Loại hóa đơn":"TD","Ngày phát hành":"02-06-2026 00:00:00","Tổng tiền":"2.146","Số điện thoại":372937559.0,"Thu ngân viên":"Bơm thủy nông","Số CTơ":2110350593.0,"Số Cột":1,"Tên Trạm":"TBA B ơm Cự Lâm Xuân Hoà"},{"Mã Sổ GCS":2265,"ID hóa đơn":1776637791.0,"Mã khách hàng":"PA09020200001","Tên khách hàng":"CTTNHH Một thành viên KTCT thủy lợi Nam Thái Bình","Địa chỉ khách hàng":"Km3, phố Quang Trung,  phường Trần Hưng Đạo, tỉnh Hưng Yên, Việt Nam","Kỳ-tháng/năm":"1-5/2026","Loại hóa đơn":"TD","Ngày phát hành":"02-06-2026 00:00:00","Tổng tiền":"1.004.309","Số điện thoại":372937559.0,"Thu ngân viên":"Bơm thủy nông","Số CTơ":20688584.0,"Số Cột":1,"Tên Trạm":"TBA B ơm Cự Lâm Xuân Hoà"},{"Mã Sổ GCS":2285,"ID hóa đơn":1775537883.0,"Mã khách hàng":"PA09020200001","Tên khách hàng":"CTTNHH Một thành viên KTCT thủy lợi Nam Thái Bình","Địa chỉ khách hàng":"Km3, phố Quang Trung,  phường Trần Hưng Đạo, tỉnh Hưng Yên, Việt Nam","Kỳ-tháng/năm":"1-5/2026","Loại hóa đơn":"TD","Ngày phát hành":"02-06-2026 00:00:00","Tổng tiền":"858.384","Số điện thoại":372937559.0,"Thu ngân viên":"Bơm thủy nông","Số CTơ":34154401.0,"Số Cột":1,"Tên Trạm":"TBA B ơm Cự Lâm Xuân Hoà"},{"Mã Sổ GCS":2320,"ID hóa đơn":1777561409.0,"Mã khách hàng":"PA09020200001","Tên khách hàng":"CTTNHH Một thành viên KTCT thủy lợi Nam Thái Bình","Địa chỉ khách hàng":"Km3, phố Quang Trung,  phường Trần Hưng Đạo, tỉnh Hưng Yên, Việt Nam","Kỳ-tháng/năm":"1-5/2026","Loại hóa đơn":"TD","Ngày phát hành":"02-06-2026 00:00:00","Tổng tiền":"787.567","Số điện thoại":372937559.0,"Thu ngân viên":"Bơm thủy nông","Số CTơ":2310336847.0,"Số Cột":1,"Tên Trạm":"TBA B ơm Cự Lâm Xuân Hoà"},{"Mã Sổ GCS":2480,"ID hóa đơn":1776669132.0,"Mã khách hàng":"PA09020200001","Tên khách hàng":"CTTNHH Một thành viên KTCT thủy lợi Nam Thái Bình","Địa chỉ khách hàng":"Km3, phố Quang Trung,  phường Trần Hưng Đạo, tỉnh Hưng Yên, Việt Nam","Kỳ-tháng/năm":"1-5/2026","Loại hóa đơn":"TD","Ngày phát hành":"02-06-2026 00:00:00","Tổng tiền":"2.176.502","Số điện thoại":372937559.0,"Thu ngân viên":"Bơm thủy nông","Số CTơ":20686666.0,"Số Cột":1,"Tên Trạm":"TBA B ơm Cự Lâm Xuân Hoà"},{"Mã Sổ GCS":2552,"ID hóa đơn":1776796247.0,"Mã khách hàng":"PA09020200001","Tên khách hàng":"CTTNHH Một thành viên KTCT thủy lợi Nam Thái Bình","Địa chỉ khách hàng":"Km3, phố Quang Trung,  phường Trần Hưng Đạo, tỉnh Hưng Yên, Việt Nam","Kỳ-tháng/năm":"1-5/2026","Loại hóa đơn":"TD","Ngày phát hành":"02-06-2026 00:00:00","Tổng tiền":"512.884","Số điện thoại":372937559.0,"Thu ngân viên":"Bơm thủy nông","Số CTơ":2210277909.0,"Số Cột":1,"Tên Trạm":"TBA B ơm Cự Lâm Xuân Hoà"},{"Mã Sổ GCS":2573,"ID hóa đơn":1776988056.0,"Mã khách hàng":"PA09020200001","Tên khách hàng":"CTTNHH Một thành viên KTCT thủy lợi Nam Thái Bình","Địa chỉ khách hàng":"Km3, phố Quang Trung,  phường Trần Hưng Đạo, tỉnh Hưng Yên, Việt Nam","Kỳ-tháng/năm":"1-5/2026","Loại hóa đơn":"TD","Ngày phát hành":"02-06-2026 00:00:00","Tổng tiền":"8.253.936","Số điện thoại":372937559.0,"Thu ngân viên":"Bơm thủy nông","Số CTơ":2110672894.0,"Số Cột":1,"Tên Trạm":"TBA B ơm Cự Lâm Xuân Hoà"},{"Mã Sổ GCS":2573,"ID hóa đơn":1776988079.0,"Mã khách hàng":"PA09020200001","Tên khách hàng":"CTTNHH Một thành viên KTCT thủy lợi Nam Thái Bình","Địa chỉ khách hàng":"Km3, phố Quang Trung,  phường Trần Hưng Đạo, tỉnh Hưng Yên, Việt Nam","Kỳ-tháng/năm":"1-5/2026","Loại hóa đơn":"VC","Ngày phát hành":"02-06-2026 00:00:00","Tổng tiền":"206.810","Số điện thoại":372937559.0,"Thu ngân viên":"Bơm thủy nông","Số CTơ":2110672894.0,"Số Cột":1,"Tên Trạm":"TBA B ơm Cự Lâm Xuân Hoà"},{"Mã Sổ GCS":2768,"ID hóa đơn":1776993118.0,"Mã khách hàng":"PA09020342590","Tên khách hàng":"CTTNHH Một thành viên KTCT thủy lợi Nam Thái Bình","Địa chỉ khách hàng":"Km số 3,  phố Quang Trung,  Phường Trần Hưng Đạo, Tỉnh Hưng Yên, Việt Nam","Kỳ-tháng/năm":"1-5/2026","Loại hóa đơn":"TD","Ngày phát hành":"02-06-2026 00:00:00","Tổng tiền":"12.876","Số điện thoại":988124675.0,"Thu ngân viên":"Bơm thủy nông","Số CTơ":2410593148.0,"Số Cột":2.2,"Tên Trạm":"Vũ Vân 10"},{"Mã Sổ GCS":2905,"ID hóa đơn":1777224499.0,"Mã khách hàng":"PA09020200001","Tên khách hàng":"CTTNHH Một thành viên KTCT thủy lợi Nam Thái Bình","Địa chỉ khách hàng":"Km3, phố Quang Trung,  phường Trần Hưng Đạo, tỉnh Hưng Yên, Việt Nam","Kỳ-tháng/năm":"1-5/2026","Loại hóa đơn":"TD","Ngày phát hành":"02-06-2026 00:00:00","Tổng tiền":"2.321.330","Số điện thoại":372937559.0,"Thu ngân viên":"Bơm thủy nông","Số CTơ":1732028541.0,"Số Cột":1,"Tên Trạm":"TBA B ơm Cự Lâm Xuân Hoà"},{"Mã Sổ GCS":"","ID hóa đơn":"","Mã khách hàng":"","Tên khách hàng":"","Địa chỉ khách hàng":"","Kỳ-tháng/năm":"Số hóa đơn: 14 HĐ","Loại hóa đơn":"","Ngày phát hành":"","Tổng tiền":"22.190.644","Số điện thoại":"","Thu ngân viên":"","Số CTơ":"","Số Cột":"","Tên Trạm":""},{"Mã Sổ GCS":"","ID hóa đơn":"","Mã khách hàng":"","Tên khách hàng":"Thu ngân viên","Địa chỉ khách hàng":"","Kỳ-tháng/năm":"","Loại hóa đơn":"Kế toán","Ngày phát hành":"","Tổng tiền":"0","Số điện thoại":"","Thu ngân viên":"Phòng kinh doanh","Số CTơ":"","Số Cột":"","Tên Trạm":""},{"Mã Sổ GCS":"","ID hóa đơn":"","Mã khách hàng":"","Tên khách hàng":"(Ký, họ tên)","Địa chỉ khách hàng":"","Kỳ-tháng/năm":"","Loại hóa đơn":"(Ký, họ tên)","Ngày phát hành":"","Tổng tiền":"0","Số điện thoại":"","Thu ngân viên":"(Ký, họ tên)","Số CTơ":"","Số Cột":"","Tên Trạm":""},{"Mã Sổ GCS":"","ID hóa đơn":"","Mã khách hàng":"","Tên khách hàng":"","Địa chỉ khách hàng":"","Kỳ-tháng/năm":"Số hóa đơn: 0 HĐ","Loại hóa đơn":"","Ngày phát hành":"","Tổng tiền":"0","Số điện thoại":"","Thu ngân viên":"","Số CTơ":"","Số Cột":"","Tên Trạm":""},{"Mã Sổ GCS":"","ID hóa đơn":"","Mã khách hàng":"","Tên khách hàng":"Thu ngân viên","Địa chỉ khách hàng":"","Kỳ-tháng/năm":"","Loại hóa đơn":"Kế toán","Ngày phát hành":"","Tổng tiền":"0","Số điện thoại":"","Thu ngân viên":"Phòng kinh doanh","Số CTơ":"","Số Cột":"","Tên Trạm":""},{"Mã Sổ GCS":"","ID hóa đơn":"","Mã khách hàng":"","Tên khách hàng":"(Ký, họ tên)","Địa chỉ khách hàng":"","Kỳ-tháng/năm":"","Loại hóa đơn":"(Ký, họ tên)","Ngày phát hành":"","Tổng tiền":"0","Số điện thoại":"","Thu ngân viên":"(Ký, họ tên)","Số CTơ":"","Số Cột":"","Tên Trạm":""},{"Mã Sổ GCS":"","ID hóa đơn":"","Mã khách hàng":"","Tên khách hàng":"","Địa chỉ khách hàng":"","Kỳ-tháng/năm":"Số hóa đơn: 0 HĐ","Loại hóa đơn":"","Ngày phát hành":"","Tổng tiền":"0","Số điện thoại":"","Thu ngân viên":"","Số CTơ":"","Số Cột":"","Tên Trạm":""},{"Mã Sổ GCS":"","ID hóa đơn":"","Mã khách hàng":"","Tên khách hàng":"Thu ngân viên","Địa chỉ khách hàng":"","Kỳ-tháng/năm":"","Loại hóa đơn":"Kế toán","Ngày phát hành":"","Tổng tiền":"0","Số điện thoại":"","Thu ngân viên":"Phòng kinh doanh","Số CTơ":"","Số Cột":"","Tên Trạm":""},{"Mã Sổ GCS":"","ID hóa đơn":"","Mã khách hàng":"","Tên khách hàng":"(Ký, họ tên)","Địa chỉ khách hàng":"","Kỳ-tháng/năm":"","Loại hóa đơn":"(Ký, họ tên)","Ngày phát hành":"","Tổng tiền":"0","Số điện thoại":"","Thu ngân viên":"(Ký, họ tên)","Số CTơ":"","Số Cột":"","Tên Trạm":""},{"Mã Sổ GCS":2207,"ID hóa đơn":1775470643.0,"Mã khách hàng":"PA09020302628","Tên khách hàng":"Phạm Thị Phượng","Địa chỉ khách hàng":"Thôn Đồng Đại 3, xã Vạn Xuân, tỉnh Hưng Yên","Kỳ-tháng/năm":"1-5/2026","Loại hóa đơn":"TD","Ngày phát hành":"02-06-2026 00:00:00","Tổng tiền":"12.856","Số điện thoại":986680715.0,"Thu ngân viên":"Thu Đồng Thanh","Số CTơ":19330505.0,"Số Cột":"2.6/1.4","Tên Trạm":"TBA Đồng Đại B Treo ( B Đồng Đại )"},{"Mã Sổ GCS":2210,"ID hóa đơn":1775470710.0,"Mã khách hàng":"PA09020220054","Tên khách hàng":"Lê Văn Cảnh","Địa chỉ khách hàng":"Thôn Thanh Hương 1, xã Vạn Xuân, tỉnh Hưng Yên","Kỳ-tháng/năm":"1-5/2026","Loại hóa đơn":"TD","Ngày phát hành":"02-06-2026 00:00:00","Tổng tiền":"12.856","Số điện thoại":865026682.0,"Thu ngân viên":"Thu Đồng Thanh","Số CTơ":18226320.0,"Số Cột":"1.13","Tên Trạm":"TBA Thanh Hương 3  RD"},{"Mã Sổ GCS":"","ID hóa đơn":"","Mã khách hàng":"","Tên khách hàng":"","Địa chỉ khách hàng":"","Kỳ-tháng/năm":"Số hóa đơn: 2 HĐ","Loại hóa đơn":"","Ngày phát hành":"","Tổng tiền":"25.712","Số điện thoại":"","Thu ngân viên":"","Số CTơ":"","Số Cột":"","Tên Trạm":""},{"Mã Sổ GCS":"","ID hóa đơn":"","Mã khách hàng":"","Tên khách hàng":"Thu ngân viên","Địa chỉ khách hàng":"","Kỳ-tháng/năm":"","Loại hóa đơn":"Kế toán","Ngày phát hành":"","Tổng tiền":"0","Số điện thoại":"","Thu ngân viên":"Phòng kinh doanh","Số CTơ":"","Số Cột":"","Tên Trạm":""},{"Mã Sổ GCS":"","ID hóa đơn":"","Mã khách hàng":"","Tên khách hàng":"(Ký, họ tên)","Địa chỉ khách hàng":"","Kỳ-tháng/năm":"","Loại hóa đơn":"(Ký, họ tên)","Ngày phát hành":"","Tổng tiền":"0","Số điện thoại":"","Thu ngân viên":"(Ký, họ tên)","Số CTơ":"","Số Cột":"","Tên Trạm":""},{"Mã Sổ GCS":"","ID hóa đơn":"","Mã khách hàng":"","Tên khách hàng":"","Địa chỉ khách hàng":"","Kỳ-tháng/năm":"Số hóa đơn: 0 HĐ","Loại hóa đơn":"","Ngày phát hành":"","Tổng tiền":"0","Số điện thoại":"","Thu ngân viên":"","Số CTơ":"","Số Cột":"","Tên Trạm":""},{"Mã Sổ GCS":"","ID hóa đơn":"","Mã khách hàng":"","Tên khách hàng":"Thu ngân viên","Địa chỉ khách hàng":"","Kỳ-tháng/năm":"","Loại hóa đơn":"Kế toán","Ngày phát hành":"","Tổng tiền":"0","Số điện thoại":"","Thu ngân viên":"Phòng kinh doanh","Số CTơ":"","Số Cột":"","Tên Trạm":""},{"Mã Sổ GCS":"","ID hóa đơn":"","Mã khách hàng":"","Tên khách hàng":"(Ký, họ tên)","Địa chỉ khách hàng":"","Kỳ-tháng/năm":"","Loại hóa đơn":"(Ký, họ tên)","Ngày phát hành":"","Tổng tiền":"0","Số điện thoại":"","Thu ngân viên":"(Ký, họ tên)","Số CTơ":"","Số Cột":"","Tên Trạm":""},{"Mã Sổ GCS":2220,"ID hóa đơn":1776551021.0,"Mã khách hàng":"PA09020232282","Tên khách hàng":"Nguyễn Văn Quỹ","Địa chỉ khách hàng":"Thôn Hành Dũng Nghĩa, xã Vũ Tiên, tỉnh Hưng Yên","Kỳ-tháng/năm":"1-5/2026","Loại hóa đơn":"TD","Ngày phát hành":"02-06-2026 00:00:00","Tổng tiền":"72.852","Số điện thoại":357689701.0,"Thu ngân viên":"Thu Duy Nhất","Số CTơ":2110272433.0,"Số Cột":"2.2/1.4","Tên Trạm":"Trạm Lê Lợi  Duy Nhất RD"},{"Mã Sổ GCS":2222,"ID hóa đơn":1776546877.0,"Mã khách hàng":"PA09020305510","Tên khách hàng":"Phạm Thị Thùy","Địa chỉ khách hàng":"Thôn Văn Thái, xã Vũ Tiên, tỉnh Hưng Yên","Kỳ-tháng/năm":"1-5/2026","Loại hóa đơn":"TD","Ngày phát hành":"02-06-2026 00:00:00","Tổng tiền":"55.711","Số điện thoại":374064486.0,"Thu ngân viên":"Thu Duy Nhất","Số CTơ":2110265536.0,"Số Cột":"2.1/1.2","Tên Trạm":"TBA Đề Thám Duy Nhất"},{"Mã Sổ GCS":2224,"ID hóa đơn":1776553160.0,"Mã khách hàng":"PA09020231427","Tên khách hàng":"Phạm Thị Nhi","Địa chỉ khách hàng":"Thôn Dũng Nhuệ, xã Vũ Tiên, tỉnh Hưng Yên","Kỳ-tháng/năm":"1-5/2026","Loại hóa đơn":"TD","Ngày phát hành":"02-06-2026 00:00:00","Tổng tiền":"764.683","Số điện thoại":926064698.0,"Thu ngân viên":"Thu Duy Nhất","Số CTơ":2110294591.0,"Số Cột":"2.7/1.3","Tên Trạm":"TBA Quang Trung"},{"Mã Sổ GCS":2224,"ID hóa đơn":1776553577.0,"Mã khách hàng":"PA09020318228","Tên khách hàng":"Nguyễn Văn Dương","Địa chỉ khách hàng":"Thôn Dũng Nhuệ, xã Vũ Tiên, tỉnh Hưng Yên","Kỳ-tháng/năm":"1-5/2026","Loại hóa đơn":"TD","Ngày phát hành":"02-06-2026 00:00:00","Tổng tiền":"269.244","Số điện thoại":987600941.0,"Thu ngân viên":"Thu Duy Nhất","Số CTơ":2110271644.0,"Số Cột":"2.8/1.3","Tên Trạm":"TBA Quang Trung"},{"Mã Sổ GCS":2230,"ID hóa đơn":1776549602.0,"Mã khách hàng":"PA09020319577","Tên khách hàng":"Nguyễn Văn Phi","Địa chỉ khách hàng":"Thôn Dũng Nhuệ, xã Vũ Tiên, tỉnh Hưng Yên","Kỳ-tháng/năm":"1-5/2026","Loại hóa đơn":"TD","Ngày phát hành":"02-06-2026 00:00:00","Tổng tiền":"72.122","Số điện thoại":378220160.0,"Thu ngân viên":"Thu Duy Nhất","Số CTơ":2110062905.0,"Số Cột":"1.4/1.1","Tên Trạm":"TBA  Bơm Vũ Nghĩa  Duy Nhất"},{"Mã Sổ GCS":2230,"ID hóa đơn":1776548952.0,"Mã khách hàng":"PA09020318124","Tên khách hàng":"Phạm Thị Lụa","Địa chỉ khách hàng":"Thôn Minh Hồng, xã Vũ Tiên, tỉnh Hưng Yên","Kỳ-tháng/năm":"1-5/2026","Loại hóa đơn":"TD","Ngày phát hành":"02-06-2026 00:00:00","Tổng tiền":"47.140","Số điện thoại":392366846.0,"Thu ngân viên":"Thu Duy Nhất","Số CTơ":2110084394.0,"Số Cột":"2.8/1.3/1.4","Tên Trạm":"TBA  Bơm Vũ Nghĩa  Duy Nhất"},{"Mã Sổ GCS":2231,"ID hóa đơn":1776546218.0,"Mã khách hàng":"PA09020226720","Tên khách hàng":"Phạm Văn Muôn","Địa chỉ khách hàng":"Thôn Minh Đức, xã Vũ Tiên, tỉnh Hưng Yên","Kỳ-tháng/năm":"1-5/2026","Loại hóa đơn":"TD","Ngày phát hành":"02-06-2026 00:00:00","Tổng tiền":"44.997","Số điện thoại":945231583.0,"Thu ngân viên":"Thu Duy Nhất","Số CTơ":2110059512.0,"Số Cột":"2.10","Tên Trạm":"TBA Minh Đức - Duy Nhất"},{"Mã Sổ GCS":2231,"ID hóa đơn":1776546417.0,"Mã khách hàng":"PA09020334484","Tên khách hàng":"Phạm Việt Thắng","Địa chỉ khách hàng":"Thôn Minh Hồng, xã Vũ Tiên, tỉnh Hưng Yên","Kỳ-tháng/năm":"1-5/2026","Loại hóa đơn":"TD","Ngày phát hành":"02-06-2026 00:00:00","Tổng tiền":"402.905","Số điện thoại":908684739.0,"Thu ngân viên":"Thu Duy Nhất","Số CTơ":2110297717.0,"Số Cột":"2.3/2.10","Tên Trạm":"TBA Minh Đức - Duy Nhất"},{"Mã Sổ GCS":2231,"ID hóa đơn":1776545780.0,"Mã khách hàng":"PA09020323528","Tên khách hàng":"Phạm Xuân Lâm","Địa chỉ khách hàng":"Thôn Minh Hồng, xã Vũ Tiên, tỉnh Hưng Yên","Kỳ-tháng/năm":"1-5/2026","Loại hóa đơn":"TD","Ngày phát hành":"02-06-2026 00:00:00","Tổng tiền":"382.249","Số điện thoại":344960667.0,"Thu ngân viên":"Thu Duy Nhất","Số CTơ":2110305122.0,"Số Cột":"2.3/2.8","Tên Trạm":"TBA Minh Đức - Duy Nhất"},{"Mã Sổ GCS":2232,"ID hóa đơn":1776550283.0,"Mã khách hàng":"PA09020323916","Tên khách hàng":"Phạm Hữu Hóa","Địa chỉ khách hàng":"Thôn Đức Long, xã Vũ Tiên, tỉnh Hưng Yên","Kỳ-tháng/năm":"1-5/2026","Loại hóa đơn":"TD","Ngày phát hành":"02-06-2026 00:00:00","Tổng tiền":"276.829","Số điện thoại":347374336.0,"Thu ngân viên":"Thu Duy Nhất","Số CTơ":20445580.0,"Số Cột":"2.10","Tên Trạm":"TBA Đức Long - Duy Nhất -RD"},{"Mã Sổ GCS":2232,"ID hóa đơn":1776550993.0,"Mã khách hàng":"PA09020228997","Tên khách hàng":"Phạm Văn Thêm","Địa chỉ khách hàng":"Thôn Đức Long, xã Vũ Tiên, tỉnh Hưng Yên","Kỳ-tháng/năm":"1-5/2026","Loại hóa đơn":"TD","Ngày phát hành":"02-06-2026 00:00:00","Tổng tiền":"51.425","Số điện thoại":912786487.0,"Thu ngân viên":"Thu Duy Nhất","Số CTơ":2110309304.0,"Số Cột":"2.10/1.2","Tên Trạm":"TBA Đức Long - Duy Nhất -RD"},{"Mã Sổ GCS":2233,"ID hóa đơn":1776549349.0,"Mã khách hàng":"PA09020319007","Tên khách hàng":"Trần Thị Mai Hạnh","Địa chỉ khách hàng":"Thôn Trung Hòa, xã Vũ Tiên, tỉnh Hưng Yên","Kỳ-tháng/năm":"1-5/2026","Loại hóa đơn":"TD","Ngày phát hành":"02-06-2026 00:00:00","Tổng tiền":"1.048.302","Số điện thoại":982748464.0,"Thu ngân viên":"Thu Duy Nhất","Số CTơ":2110062745.0,"Số Cột":"1.12","Tên Trạm":"TBA Nam Long  Duy Nhất"},{"Mã Sổ GCS":2233,"ID hóa đơn":1776549259.0,"Mã khách hàng":"PA09020231309","Tên khách hàng":"Phạm Trung Thành","Địa chỉ khách hàng":"Thôn Thiện Long, xã Vũ Tiên, tỉnh Hưng Yên","Kỳ-tháng/năm":"1-5/2026","Loại hóa đơn":"TD","Ngày phát hành":"02-06-2026 00:00:00","Tổng tiền":"312.941","Số điện thoại":383507347.0,"Thu ngân viên":"Thu Duy Nhất","Số CTơ":2110072355.0,"Số Cột":"2.2/1.1","Tên Trạm":"TBA Nam Long  Duy Nhất"},{"Mã Sổ GCS":2234,"ID hóa đơn":1776544981.0,"Mã khách hàng":"PA09020232446","Tên khách hàng":"Phạm Văn Bao","Địa chỉ khách hàng":"Thôn Hành Dũng Nghĩa, xã Vũ Tiên, tỉnh Hưng Yên","Kỳ-tháng/năm":"1-5/2026","Loại hóa đơn":"TD","Ngày phát hành":"02-06-2026 00:00:00","Tổng tiền":"29.998","Số điện thoại":357436281.0,"Thu ngân viên":"Thu Duy Nhất","Số CTơ":2110298928.0,"Số Cột":"1.19","Tên Trạm":"TBA Vũ Đoài Bãi -Xóm 15 Vũ Nghĩa"},{"Mã Sổ GCS":2235,"ID hóa đơn":1776546946.0,"Mã khách hàng":"PA09020233751","Tên khách hàng":"Nguyễn Văn Nguyên","Địa chỉ khách hàng":"Thôn Thiện Long, xã Vũ Tiên, tỉnh Hưng Yên","Kỳ-tháng/năm":"1-5/2026","Loại hóa đơn":"TD","Ngày phát hành":"02-06-2026 00:00:00","Tổng tiền":"716.416","Số điện thoại":374880422.0,"Thu ngân viên":"Thu Duy Nhất","Số CTơ":2110268742.0,"Số Cột":"1.7","Tên Trạm":"TBA Tả Hành ( Cống Na ) Duy Nhất"},{"Mã Sổ GCS":2235,"ID hóa đơn":1776546533.0,"Mã khách hàng":"PA09020232464","Tên khách hàng":"Tống Xuân Thuỷ","Địa chỉ khách hàng":"Thôn Thiện Long, xã Vũ Tiên, tỉnh Hưng Yên","Kỳ-tháng/năm":"1-5/2026","Loại hóa đơn":"TD","Ngày phát hành":"02-06-2026 00:00:00","Tổng tiền":"438.242","Số điện thoại":327159064.0,"Thu ngân viên":"Thu Duy Nhất","Số CTơ":2110296831.0,"Số Cột":"1.9","Tên Trạm":"TBA Tả Hành ( Cống Na ) Duy Nhất"},{"Mã Sổ GCS":2235,"ID hóa đơn":1776546541.0,"Mã khách hàng":"PA09020232477","Tên khách hàng":"Nguyễn Văn Thông","Địa chỉ khách hàng":"Thôn Thiện Long, xã Vũ Tiên, tỉnh Hưng Yên","Kỳ-tháng/năm":"1-5/2026","Loại hóa đơn":"TD","Ngày phát hành":"02-06-2026 00:00:00","Tổng tiền":"32.141","Số điện thoại":387757940.0,"Thu ngân viên":"Thu Duy Nhất","Số CTơ":2110298262.0,"Số Cột":"1.9/1.1","Tên Trạm":"TBA Tả Hành ( Cống Na ) Duy Nhất"},{"Mã Sổ GCS":2237,"ID hóa đơn":1776548805.0,"Mã khách hàng":"PA09020235619","Tên khách hàng":"Phạm Ngọc Ưng","Địa chỉ khách hàng":"Thôn Thiện Long, xã Vũ Tiên, tỉnh Hưng Yên","Kỳ-tháng/năm":"1-5/2026","Loại hóa đơn":"TD","Ngày phát hành":"02-06-2026 00:00:00","Tổng tiền":"333.504","Số điện thoại":379635789.0,"Thu ngân viên":"Thu Duy Nhất","Số CTơ":2110071421.0,"Số Cột":"2.12/1.1","Tên Trạm":"TBA Vũ Nghĩa 2 xã Duy Nhất"},{"Mã Sổ GCS":2237,"ID hóa đơn":1776548254.0,"Mã khách hàng":"PA09020235616","Tên khách hàng":"Phạm Trọng Hinh","Địa chỉ khách hàng":"Thôn Thiện Long, xã Vũ Tiên, tỉnh Hưng Yên","Kỳ-tháng/năm":"1-5/2026","Loại hóa đơn":"TD","Ngày phát hành":"02-06-2026 00:00:00","Tổng tiền":"243.540","Số điện thoại":978828241.0,"Thu ngân viên":"Thu Duy Nhất","Số CTơ":2110278347.0,"Số Cột":"2.24","Tên Trạm":"TBA Vũ Nghĩa 2 xã Duy Nhất"},{"Mã Sổ GCS":2237,"ID hóa đơn":1776548782.0,"Mã khách hàng":"PA09020349709","Tên khách hàng":"Phạm Văn Giới","Địa chỉ khách hàng":"Thôn Minh Hồng, Xã Vũ Tiên Tỉnh Hưng Yên","Kỳ-tháng/năm":"1-5/2026","Loại hóa đơn":"TD","Ngày phát hành":"02-06-2026 00:00:00","Tổng tiền":"49.283","Số điện thoại":964269862.0,"Thu ngân viên":"Thu Duy Nhất","Số CTơ":2411353705.0,"Số Cột":"3.8","Tên Trạm":"TBA Vũ Nghĩa 2 xã Duy Nhất"},{"Mã Sổ GCS":"","ID hóa đơn":"","Mã khách hàng":"","Tên khách hàng":"","Địa chỉ khách hàng":"","Kỳ-tháng/năm":"Số hóa đơn: 20 HĐ","Loại hóa đơn":"","Ngày phát hành":"","Tổng tiền":"5.644.524","Số điện thoại":"","Thu ngân viên":"","Số CTơ":"","Số Cột":"","Tên Trạm":""},{"Mã Sổ GCS":"","ID hóa đơn":"","Mã khách hàng":"","Tên khách hàng":"Thu ngân viên","Địa chỉ khách hàng":"","Kỳ-tháng/năm":"","Loại hóa đơn":"Kế toán","Ngày phát hành":"","Tổng tiền":"0","Số điện thoại":"","Thu ngân viên":"Phòng kinh doanh","Số CTơ":"","Số Cột":"","Tên Trạm":""},{"Mã Sổ GCS":"","ID hóa đơn":"","Mã khách hàng":"","Tên khách hàng":"(Ký, họ tên)","Địa chỉ khách hàng":"","Kỳ-tháng/năm":"","Loại hóa đơn":"(Ký, họ tên)","Ngày phát hành":"","Tổng tiền":"0","Số điện thoại":"","Thu ngân viên":"(Ký, họ tên)","Số CTơ":"","Số Cột":"","Tên Trạm":""},{"Mã Sổ GCS":"","ID hóa đơn":"","Mã khách hàng":"","Tên khách hàng":"","Địa chỉ khách hàng":"","Kỳ-tháng/năm":"Số hóa đơn: 0 HĐ","Loại hóa đơn":"","Ngày phát hành":"","Tổng tiền":"0","Số điện thoại":"","Thu ngân viên":"","Số CTơ":"","Số Cột":"","Tên Trạm":""},{"Mã Sổ GCS":"","ID hóa đơn":"","Mã khách hàng":"","Tên khách hàng":"Thu ngân viên","Địa chỉ khách hàng":"","Kỳ-tháng/năm":"","Loại hóa đơn":"Kế toán","Ngày phát hành":"","Tổng tiền":"0","Số điện thoại":"","Thu ngân viên":"Phòng kinh doanh","Số CTơ":"","Số Cột":"","Tên Trạm":""},{"Mã Sổ GCS":"","ID hóa đơn":"","Mã khách hàng":"","Tên khách hàng":"(Ký, họ tên)","Địa chỉ khách hàng":"","Kỳ-tháng/năm":"","Loại hóa đơn":"(Ký, họ tên)","Ngày phát hành":"","Tổng tiền":"0","Số điện thoại":"","Thu ngân viên":"(Ký, họ tên)","Số CTơ":"","Số Cột":"","Tên Trạm":""},{"Mã Sổ GCS":"","ID hóa đơn":"","Mã khách hàng":"","Tên khách hàng":"","Địa chỉ khách hàng":"","Kỳ-tháng/năm":"Số hóa đơn: 0 HĐ","Loại hóa đơn":"","Ngày phát hành":"","Tổng tiền":"0","Số điện thoại":"","Thu ngân viên":"","Số CTơ":"","Số Cột":"","Tên Trạm":""},{"Mã Sổ GCS":"","ID hóa đơn":"","Mã khách hàng":"","Tên khách hàng":"Thu ngân viên","Địa chỉ khách hàng":"","Kỳ-tháng/năm":"","Loại hóa đơn":"Kế toán","Ngày phát hành":"","Tổng tiền":"0","Số điện thoại":"","Thu ngân viên":"Phòng kinh doanh","Số CTơ":"","Số Cột":"","Tên Trạm":""},{"Mã Sổ GCS":"","ID hóa đơn":"","Mã khách hàng":"","Tên khách hàng":"(Ký, họ tên)","Địa chỉ khách hàng":"","Kỳ-tháng/năm":"","Loại hóa đơn":"(Ký, họ tên)","Ngày phát hành":"","Tổng tiền":"0","Số điện thoại":"","Thu ngân viên":"(Ký, họ tên)","Số CTơ":"","Số Cột":"","Tên Trạm":""},{"Mã Sổ GCS":2267,"ID hóa đơn":1776637335.0,"Mã khách hàng":"PA09020229407","Tên khách hàng":"Nguyễn Công Thắng","Địa chỉ khách hàng":"Thôn Thượng Hộ Nam, xã Vạn Xuân, tỉnh Hưng Yên","Kỳ-tháng/năm":"1-5/2026","Loại hóa đơn":"TD","Ngày phát hành":"02-06-2026 00:00:00","Tổng tiền":"220.406","Số điện thoại":372991143.0,"Thu ngân viên":"Thu Hồng Lý","Số CTơ":21024635.0,"Số Cột":1.6,"Tên Trạm":"TBA Thượng hộ nam  Hồng Lý - RD"},{"Mã Sổ GCS":"","ID hóa đơn":"","Mã khách hàng":"","Tên khách hàng":"","Địa chỉ khách hàng":"","Kỳ-tháng/năm":"Số hóa đơn: 1 HĐ","Loại hóa đơn":"","Ngày phát hành":"","Tổng tiền":"220.406","Số điện thoại":"","Thu ngân viên":"","Số CTơ":"","Số Cột":"","Tên Trạm":""},{"Mã Sổ GCS":"","ID hóa đơn":"","Mã khách hàng":"","Tên khách hàng":"Thu ngân viên","Địa chỉ khách hàng":"","Kỳ-tháng/năm":"","Loại hóa đơn":"Kế toán","Ngày phát hành":"","Tổng tiền":"0","Số điện thoại":"","Thu ngân viên":"Phòng kinh doanh","Số CTơ":"","Số Cột":"","Tên Trạm":""},{"Mã Sổ GCS":"","ID hóa đơn":"","Mã khách hàng":"","Tên khách hàng":"(Ký, họ tên)","Địa chỉ khách hàng":"","Kỳ-tháng/năm":"","Loại hóa đơn":"(Ký, họ tên)","Ngày phát hành":"","Tổng tiền":"0","Số điện thoại":"","Thu ngân viên":"(Ký, họ tên)","Số CTơ":"","Số Cột":"","Tên Trạm":""},{"Mã Sổ GCS":2134,"ID hóa đơn":1777091008.0,"Mã khách hàng":"PA09020211085","Tên khách hàng":"Đinh Thị Nụng","Địa chỉ khách hàng":"Thôn Kênh đào, xã Vũ Tiên, tỉnh Hưng Yên","Kỳ-tháng/năm":"1-5/2026","Loại hóa đơn":"TD","Ngày phát hành":"02-06-2026 00:00:00","Tổng tiền":"763.044","Số điện thoại":383727469.0,"Thu ngân viên":"Thu Hồng Phong","Số CTơ":18212530.0,"Số Cột":"1.1/1.3","Tên Trạm":"TBA Kênh Đào Hồng Phong"},{"Mã Sổ GCS":"","ID hóa đơn":"","Mã khách hàng":"","Tên khách hàng":"","Địa chỉ khách hàng":"","Kỳ-tháng/năm":"Số hóa đơn: 1 HĐ","Loại hóa đơn":"","Ngày phát hành":"","Tổng tiền":"763.044","Số điện thoại":"","Thu ngân viên":"","Số CTơ":"","Số Cột":"","Tên Trạm":""},{"Mã Sổ GCS":"","ID hóa đơn":"","Mã khách hàng":"","Tên khách hàng":"Thu ngân viên","Địa chỉ khách hàng":"","Kỳ-tháng/năm":"","Loại hóa đơn":"Kế toán","Ngày phát hành":"","Tổng tiền":"0","Số điện thoại":"","Thu ngân viên":"Phòng kinh doanh","Số CTơ":"","Số Cột":"","Tên Trạm":""},{"Mã Sổ GCS":"","ID hóa đơn":"","Mã khách hàng":"","Tên khách hàng":"(Ký, họ tên)","Địa chỉ khách hàng":"","Kỳ-tháng/năm":"","Loại hóa đơn":"(Ký, họ tên)","Ngày phát hành":"","Tổng tiền":"0","Số điện thoại":"","Thu ngân viên":"(Ký, họ tên)","Số CTơ":"","Số Cột":"","Tên Trạm":""},{"Mã Sổ GCS":2509,"ID hóa đơn":1777388598.0,"Mã khách hàng":"PA09020319248","Tên khách hàng":"Hội trường thôn Thọ Lộc","Địa chỉ khách hàng":"Thôn Thọ Lộc, xã Vũ Thư, tỉnh Hưng Yên","Kỳ-tháng/năm":"1-5/2026","Loại hóa đơn":"TD","Ngày phát hành":"02-06-2026 00:00:00","Tổng tiền":"69.718","Số điện thoại":972310978.0,"Thu ngân viên":"Thu Minh Khai","Số CTơ":2110784408.0,"Số Cột":1.8,"Tên Trạm":"TBA Thọ Lộc Minh Khai"},{"Mã Sổ GCS":"","ID hóa đơn":"","Mã khách hàng":"","Tên khách hàng":"","Địa chỉ khách hàng":"","Kỳ-tháng/năm":"Số hóa đơn: 1 HĐ","Loại hóa đơn":"","Ngày phát hành":"","Tổng tiền":"69.718","Số điện thoại":"","Thu ngân viên":"","Số CTơ":"","Số Cột":"","Tên Trạm":""},{"Mã Sổ GCS":"","ID hóa đơn":"","Mã khách hàng":"","Tên khách hàng":"Thu ngân viên","Địa chỉ khách hàng":"","Kỳ-tháng/năm":"","Loại hóa đơn":"Kế toán","Ngày phát hành":"","Tổng tiền":"0","Số điện thoại":"","Thu ngân viên":"Phòng kinh doanh","Số CTơ":"","Số Cột":"","Tên Trạm":""},{"Mã Sổ GCS":"","ID hóa đơn":"","Mã khách hàng":"","Tên khách hàng":"(Ký, họ tên)","Địa chỉ khách hàng":"","Kỳ-tháng/năm":"","Loại hóa đơn":"(Ký, họ tên)","Ngày phát hành":"","Tổng tiền":"0","Số điện thoại":"","Thu ngân viên":"(Ký, họ tên)","Số CTơ":"","Số Cột":"","Tên Trạm":""},{"Mã Sổ GCS":"","ID hóa đơn":"","Mã khách hàng":"","Tên khách hàng":"","Địa chỉ khách hàng":"","Kỳ-tháng/năm":"Số hóa đơn: 0 HĐ","Loại hóa đơn":"","Ngày phát hành":"","Tổng tiền":"0","Số điện thoại":"","Thu ngân viên":"","Số CTơ":"","Số Cột":"","Tên Trạm":""},{"Mã Sổ GCS":"","ID hóa đơn":"","Mã khách hàng":"","Tên khách hàng":"Thu ngân viên","Địa chỉ khách hàng":"","Kỳ-tháng/năm":"","Loại hóa đơn":"Kế toán","Ngày phát hành":"","Tổng tiền":"0","Số điện thoại":"","Thu ngân viên":"Phòng kinh doanh","Số CTơ":"","Số Cột":"","Tên Trạm":""},{"Mã Sổ GCS":"","ID hóa đơn":"","Mã khách hàng":"","Tên khách hàng":"(Ký, họ tên)","Địa chỉ khách hàng":"","Kỳ-tháng/năm":"","Loại hóa đơn":"(Ký, họ tên)","Ngày phát hành":"","Tổng tiền":"0","Số điện thoại":"","Thu ngân viên":"(Ký, họ tên)","Số CTơ":"","Số Cột":"","Tên Trạm":""},{"Mã Sổ GCS":2150,"ID hóa đơn":1776496380.0,"Mã khách hàng":"PA09020243431","Tên khách hàng":"Hội trường thôn Huyền Sỹ","Địa chỉ khách hàng":"Thôn Huyền Sỹ, xã Vũ Thư, tỉnh Hưng Yên","Kỳ-tháng/năm":"1-5/2026","Loại hóa đơn":"TD","Ngày phát hành":"02-06-2026 00:00:00","Tổng tiền":"88.951","Số điện thoại":989267435.0,"Thu ngân viên":"Thu Minh Quang","Số CTơ":2111434500.0,"Số Cột":"1.10","Tên Trạm":"TBA Huyền Sỹ Minh Quang"},{"Mã Sổ GCS":2152,"ID hóa đơn":1776496173.0,"Mã khách hàng":"PA09020212943","Tên khách hàng":"Hội trường thôn Trực Nho","Địa chỉ khách hàng":"Thôn Trực Nho,  Xã Vũ Thư, tỉnh Hưng Yên","Kỳ-tháng/năm":"1-5/2026","Loại hóa đơn":"TD","Ngày phát hành":"02-06-2026 00:00:00","Tổng tiền":"298.106","Số điện thoại":989267435.0,"Thu ngân viên":"Thu Minh Quang","Số CTơ":2111398378.0,"Số Cột":"1.9","Tên Trạm":"TBA TRỰC NHO 2 MINH QUANG"},{"Mã Sổ GCS":2154,"ID hóa đơn":1776494292.0,"Mã khách hàng":"PA09020243335","Tên khách hàng":"Hội trường thôn Minh Quàn","Địa chỉ khách hàng":"Thôn Minh Quàn,  Xã Vũ Thư, tỉnh Hưng Yên","Kỳ-tháng/năm":"1-5/2026","Loại hóa đơn":"TD","Ngày phát hành":"02-06-2026 00:00:00","Tổng tiền":"117.800","Số điện thoại":989267435.0,"Thu ngân viên":"Thu Minh Quang","Số CTơ":2111394297.0,"Số Cột":"1.4/1.4","Tên Trạm":"TBA xóm 14 minh quàn M quang"},{"Mã Sổ GCS":2155,"ID hóa đơn":1776496795.0,"Mã khách hàng":"PA09020318443","Tên khách hàng":"Hội trường thôn La Uyên","Địa chỉ khách hàng":"Thôn La Uyên,  Xã Vũ Thư, tỉnh Hưng Yên","Kỳ-tháng/năm":"1-5/2026","Loại hóa đơn":"TD","Ngày phát hành":"02-06-2026 00:00:00","Tổng tiền":"60.102","Số điện thoại":989267435.0,"Thu ngân viên":"Thu Minh Quang","Số CTơ":2210527034.0,"Số Cột":"2.4/1.1","Tên Trạm":"TBA Truyền Thanh(La Uyên) M Quang"},{"Mã Sổ GCS":2157,"ID hóa đơn":1776497566.0,"Mã khách hàng":"PA09020239714","Tên khách hàng":"Hội Trường Thôn La nguyễn","Địa chỉ khách hàng":"Thôn La Nguyễn,  Xã Vũ Thư, tỉnh Hưng Yên","Kỳ-tháng/năm":"1-5/2026","Loại hóa đơn":"TD","Ngày phát hành":"02-06-2026 00:00:00","Tổng tiền":"69.718","Số điện thoại":338840994.0,"Thu ngân viên":"Thu Minh Quang","Số CTơ":2111430233.0,"Số Cột":"2.12","Tên Trạm":"TBA La Nguyễn xã Minh Quang (RD)"},{"Mã Sổ GCS":"","ID hóa đơn":"","Mã khách hàng":"","Tên khách hàng":"","Địa chỉ khách hàng":"","Kỳ-tháng/năm":"Số hóa đơn: 5 HĐ","Loại hóa đơn":"","Ngày phát hành":"","Tổng tiền":"634.677","Số điện thoại":"","Thu ngân viên":"","Số CTơ":"","Số Cột":"","Tên Trạm":""},{"Mã Sổ GCS":"","ID hóa đơn":"","Mã khách hàng":"","Tên khách hàng":"Thu ngân viên","Địa chỉ khách hàng":"","Kỳ-tháng/năm":"","Loại hóa đơn":"Kế toán","Ngày phát hành":"","Tổng tiền":"0","Số điện thoại":"","Thu ngân viên":"Phòng kinh doanh","Số CTơ":"","Số Cột":"","Tên Trạm":""},{"Mã Sổ GCS":"","ID hóa đơn":"","Mã khách hàng":"","Tên khách hàng":"(Ký, họ tên)","Địa chỉ khách hàng":"","Kỳ-tháng/năm":"","Loại hóa đơn":"(Ký, họ tên)","Ngày phát hành":"","Tổng tiền":"0","Số điện thoại":"","Thu ngân viên":"(Ký, họ tên)","Số CTơ":"","Số Cột":"","Tên Trạm":""},{"Mã Sổ GCS":2555,"ID hóa đơn":1776819052.0,"Mã khách hàng":"PA09020321960","Tên khách hàng":"Nguyễn Ngọc Oánh","Địa chỉ khách hàng":"Thôn Trung, xã Thư Trì, tỉnh Hưng Yên","Kỳ-tháng/năm":"1-5/2026","Loại hóa đơn":"TD","Ngày phát hành":"02-06-2026 00:00:00","Tổng tiền":"166.914","Số điện thoại":356142555.0,"Thu ngân viên":"Thu Song Lãng","Số CTơ":2111404763.0,"Số Cột":"2.10","Tên Trạm":"TBA THÔN TRUNG 2"},{"Mã Sổ GCS":2556,"ID hóa đơn":1776799897.0,"Mã khách hàng":"PA09020321141","Tên khách hàng":"Lê Thị Khánh","Địa chỉ khách hàng":"Thôn Trung, xã Thư Trì, tỉnh Hưng Yên","Kỳ-tháng/năm":"1-5/2026","Loại hóa đơn":"TD","Ngày phát hành":"02-06-2026 00:00:00","Tổng tiền":"230.688","Số điện thoại":382498210.0,"Thu ngân viên":"Thu Song Lãng","Số CTơ":2111379246.0,"Số Cột":"1.5/1.4/1.1","Tên Trạm":"TBA THÔN TRUNG"},{"Mã Sổ GCS":2558,"ID hóa đơn":1776798056.0,"Mã khách hàng":"PA09020332483","Tên khách hàng":"Lê Bá Nhiệm","Địa chỉ khách hàng":"Thôn Trung, xã Thư Trì, tỉnh Hưng Yên","Kỳ-tháng/năm":"1-5/2026","Loại hóa đơn":"TD","Ngày phát hành":"02-06-2026 00:00:00","Tổng tiền":"548.130","Số điện thoại":866976226.0,"Thu ngân viên":"Thu Song Lãng","Số CTơ":2111390735.0,"Số Cột":"2.8","Tên Trạm":"TBA Thôn Trung 3 xã Song Lãng"},{"Mã Sổ GCS":"","ID hóa đơn":"","Mã khách hàng":"","Tên khách hàng":"","Địa chỉ khách hàng":"","Kỳ-tháng/năm":"Số hóa đơn: 3 HĐ","Loại hóa đơn":"","Ngày phát hành":"","Tổng tiền":"945.732","Số điện thoại":"","Thu ngân viên":"","Số CTơ":"","Số Cột":"","Tên Trạm":""},{"Mã Sổ GCS":"","ID hóa đơn":"","Mã khách hàng":"","Tên khách hàng":"Thu ngân viên","Địa chỉ khách hàng":"","Kỳ-tháng/năm":"","Loại hóa đơn":"Kế toán","Ngày phát hành":"","Tổng tiền":"0","Số điện thoại":"","Thu ngân viên":"Phòng kinh doanh","Số CTơ":"","Số Cột":"","Tên Trạm":""},{"Mã Sổ GCS":"","ID hóa đơn":"","Mã khách hàng":"","Tên khách hàng":"(Ký, họ tên)","Địa chỉ khách hàng":"","Kỳ-tháng/năm":"","Loại hóa đơn":"(Ký, họ tên)","Ngày phát hành":"","Tổng tiền":"0","Số điện thoại":"","Thu ngân viên":"(Ký, họ tên)","Số CTơ":"","Số Cột":"","Tên Trạm":""},{"Mã Sổ GCS":"","ID hóa đơn":"","Mã khách hàng":"","Tên khách hàng":"","Địa chỉ khách hàng":"","Kỳ-tháng/năm":"Số hóa đơn: 0 HĐ","Loại hóa đơn":"","Ngày phát hành":"","Tổng tiền":"0","Số điện thoại":"","Thu ngân viên":"","Số CTơ":"","Số Cột":"","Tên Trạm":""},{"Mã Sổ GCS":"","ID hóa đơn":"","Mã khách hàng":"","Tên khách hàng":"Thu ngân viên","Địa chỉ khách hàng":"","Kỳ-tháng/năm":"","Loại hóa đơn":"Kế toán","Ngày phát hành":"","Tổng tiền":"0","Số điện thoại":"","Thu ngân viên":"Phòng kinh doanh","Số CTơ":"","Số Cột":"","Tên Trạm":""},{"Mã Sổ GCS":"","ID hóa đơn":"","Mã khách hàng":"","Tên khách hàng":"(Ký, họ tên)","Địa chỉ khách hàng":"","Kỳ-tháng/năm":"","Loại hóa đơn":"(Ký, họ tên)","Ngày phát hành":"","Tổng tiền":"0","Số điện thoại":"","Thu ngân viên":"(Ký, họ tên)","Số CTơ":"","Số Cột":"","Tên Trạm":""},{"Mã Sổ GCS":"","ID hóa đơn":"","Mã khách hàng":"","Tên khách hàng":"","Địa chỉ khách hàng":"","Kỳ-tháng/năm":"Số hóa đơn: 0 HĐ","Loại hóa đơn":"","Ngày phát hành":"","Tổng tiền":"0","Số điện thoại":"","Thu ngân viên":"","Số CTơ":"","Số Cột":"","Tên Trạm":""},{"Mã Sổ GCS":"","ID hóa đơn":"","Mã khách hàng":"","Tên khách hàng":"Thu ngân viên","Địa chỉ khách hàng":"","Kỳ-tháng/năm":"","Loại hóa đơn":"Kế toán","Ngày phát hành":"","Tổng tiền":"0","Số điện thoại":"","Thu ngân viên":"Phòng kinh doanh","Số CTơ":"","Số Cột":"","Tên Trạm":""},{"Mã Sổ GCS":"","ID hóa đơn":"","Mã khách hàng":"","Tên khách hàng":"(Ký, họ tên)","Địa chỉ khách hàng":"","Kỳ-tháng/năm":"","Loại hóa đơn":"(Ký, họ tên)","Ngày phát hành":"","Tổng tiền":"0","Số điện thoại":"","Thu ngân viên":"(Ký, họ tên)","Số CTơ":"","Số Cột":"","Tên Trạm":""},{"Mã Sổ GCS":2572,"ID hóa đơn":1776991622.0,"Mã khách hàng":"PA0902TVT7794","Tên khách hàng":"Hội trường khu Hùng tiến","Địa chỉ khách hàng":"Tổ Hùng Tiến, xã Vũ Thư, tỉnh Hưng Yên","Kỳ-tháng/năm":"1-5/2026","Loại hóa đơn":"TD","Ngày phát hành":"02-06-2026 00:00:00","Tổng tiền":"48.082","Số điện thoại":987626798.0,"Thu ngân viên":"Thu Thị trấn","Số CTơ":18117291.0,"Số Cột":"3.7/1.2","Tên Trạm":"TBA Kho Muối 2"},{"Mã Sổ GCS":2573,"ID hóa đơn":1776989773.0,"Mã khách hàng":"PA0902TVT0338","Tên khách hàng":"Hội trường khu Trung hưng 1","Địa chỉ khách hàng":"Khu Trung Hưng, xã Vũ Thư, tỉnh Hưng Yên","Kỳ-tháng/năm":"1-5/2026","Loại hóa đơn":"TD","Ngày phát hành":"02-06-2026 00:00:00","Tổng tiền":"50.486","Số điện thoại":987046566.0,"Thu ngân viên":"Thu Thị trấn","Số CTơ":18116106.0,"Số Cột":"3.10/1.2","Tên Trạm":"TBA  Bơm Song An"},{"Mã Sổ GCS":2585,"ID hóa đơn":1776988091.0,"Mã khách hàng":"PA0902TVT7789","Tên khách hàng":"Hội trường khu Trung hưng  3","Địa chỉ khách hàng":"Tổ Trung Hưng, xã Vũ Thư, tỉnh Hưng Yên","Kỳ-tháng/năm":"1-5/2026","Loại hóa đơn":"TD","Ngày phát hành":"02-06-2026 00:00:00","Tổng tiền":"149.053","Số điện thoại":378291027.0,"Thu ngân viên":"Thu Thị trấn","Số CTơ":18116608.0,"Số Cột":"1.8/2.1","Tên Trạm":"TBA Chiếu sáng QL10(Số10) "},{"Mã Sổ GCS":2586,"ID hóa đơn":1776989450.0,"Mã khách hàng":"PA09020306724","Tên khách hàng":"Hội trường khu Minh Tân 2","Địa chỉ khách hàng":"Thôn Minh Hưng, xã Vũ Thư, tỉnh Hưng Yên","Kỳ-tháng/năm":"1-5/2026","Loại hóa đơn":"TD","Ngày phát hành":"02-06-2026 00:00:00","Tổng tiền":"153.861","Số điện thoại":868921963.0,"Thu ngân viên":"Thu Thị trấn","Số CTơ":18116798.0,"Số Cột":"2.4","Tên Trạm":"TBA Chợ Thẫm 3 Thị Trấn Vũ Thư"},{"Mã Sổ GCS":"","ID hóa đơn":"","Mã khách hàng":"","Tên khách hàng":"","Địa chỉ khách hàng":"","Kỳ-tháng/năm":"Số hóa đơn: 4 HĐ","Loại hóa đơn":"","Ngày phát hành":"","Tổng tiền":"401.482","Số điện thoại":"","Thu ngân viên":"","Số CTơ":"","Số Cột":"","Tên Trạm":""},{"Mã Sổ GCS":"","ID hóa đơn":"","Mã khách hàng":"","Tên khách hàng":"Thu ngân viên","Địa chỉ khách hàng":"","Kỳ-tháng/năm":"","Loại hóa đơn":"Kế toán","Ngày phát hành":"","Tổng tiền":"0","Số điện thoại":"","Thu ngân viên":"Phòng kinh doanh","Số CTơ":"","Số Cột":"","Tên Trạm":""},{"Mã Sổ GCS":"","ID hóa đơn":"","Mã khách hàng":"","Tên khách hàng":"(Ký, họ tên)","Địa chỉ khách hàng":"","Kỳ-tháng/năm":"","Loại hóa đơn":"(Ký, họ tên)","Ngày phát hành":"","Tổng tiền":"0","Số điện thoại":"","Thu ngân viên":"(Ký, họ tên)","Số CTơ":"","Số Cột":"","Tên Trạm":""},{"Mã Sổ GCS":2652,"ID hóa đơn":1777243807.0,"Mã khách hàng":"PA09020329289","Tên khách hàng":"Phạm Văn Nhưỡng","Địa chỉ khách hàng":"Thôn Phú Lễ 1, xã Tân Thuận, tỉnh Hưng Yên","Kỳ-tháng/năm":"1-5/2026","Loại hóa đơn":"TD","Ngày phát hành":"02-06-2026 00:00:00","Tổng tiền":"64.282","Số điện thoại":913458648.0,"Thu ngân viên":"Thu Tự Tân","Số CTơ":2210281417.0,"Số Cột":"2.4/1.3/1.4","Tên Trạm":"TBA Bơm Phú Lễ"},{"Mã Sổ GCS":"","ID hóa đơn":"","Mã khách hàng":"","Tên khách hàng":"","Địa chỉ khách hàng":"","Kỳ-tháng/năm":"Số hóa đơn: 1 HĐ","Loại hóa đơn":"","Ngày phát hành":"","Tổng tiền":"64.282","Số điện thoại":"","Thu ngân viên":"","Số CTơ":"","Số Cột":"","Tên Trạm":""},{"Mã Sổ GCS":"","ID hóa đơn":"","Mã khách hàng":"","Tên khách hàng":"Thu ngân viên","Địa chỉ khách hàng":"","Kỳ-tháng/năm":"","Loại hóa đơn":"Kế toán","Ngày phát hành":"","Tổng tiền":"0","Số điện thoại":"","Thu ngân viên":"Phòng kinh doanh","Số CTơ":"","Số Cột":"","Tên Trạm":""},{"Mã Sổ GCS":"","ID hóa đơn":"","Mã khách hàng":"","Tên khách hàng":"(Ký, họ tên)","Địa chỉ khách hàng":"","Kỳ-tháng/năm":"","Loại hóa đơn":"(Ký, họ tên)","Ngày phát hành":"","Tổng tiền":"0","Số điện thoại":"","Thu ngân viên":"(Ký, họ tên)","Số CTơ":"","Số Cột":"","Tên Trạm":""},{"Mã Sổ GCS":2473,"ID hóa đơn":1776671898.0,"Mã khách hàng":"PA0902VH00052","Tên khách hàng":"Nguyễn Thị Lâm","Địa chỉ khách hàng":"Thôn Mỹ Lộc, xã Vạn Xuân, tỉnh Hưng Yên","Kỳ-tháng/năm":"1-5/2026","Loại hóa đơn":"TD","Ngày phát hành":"02-06-2026 00:00:00","Tổng tiền":"19.284","Số điện thoại":868280799.0,"Thu ngân viên":"Thu Việt Hùng","Số CTơ":2310446424.0,"Số Cột":"1.8","Tên Trạm":"Ủy ban nhân dân xã Việt Hùng (RD)"},{"Mã Sổ GCS":2484,"ID hóa đơn":1776668965.0,"Mã khách hàng":"PA0902VH02194","Tên khách hàng":"Trương Văn Thú","Địa chỉ khách hàng":"Xóm 4, thôn Lộc Điền, xã Vạn Xuân, tỉnh Hưng Yên","Kỳ-tháng/năm":"1-5/2026","Loại hóa đơn":"TD","Ngày phát hành":"02-06-2026 00:00:00","Tổng tiền":"47.140","Số điện thoại":349346159.0,"Thu ngân viên":"Thu Việt Hùng","Số CTơ":2310508575.0,"Số Cột":"1.7/1.2","Tên Trạm":"TBA PHÚ LỘC 3 VIỆT HÙNG"},{"Mã Sổ GCS":"","ID hóa đơn":"","Mã khách hàng":"","Tên khách hàng":"","Địa chỉ khách hàng":"","Kỳ-tháng/năm":"Số hóa đơn: 2 HĐ","Loại hóa đơn":"","Ngày phát hành":"","Tổng tiền":"66.424","Số điện thoại":"","Thu ngân viên":"","Số CTơ":"","Số Cột":"","Tên Trạm":""},{"Mã Sổ GCS":"","ID hóa đơn":"","Mã khách hàng":"","Tên khách hàng":"Thu ngân viên","Địa chỉ khách hàng":"","Kỳ-tháng/năm":"","Loại hóa đơn":"Kế toán","Ngày phát hành":"","Tổng tiền":"0","Số điện thoại":"","Thu ngân viên":"Phòng kinh doanh","Số CTơ":"","Số Cột":"","Tên Trạm":""},{"Mã Sổ GCS":"","ID hóa đơn":"","Mã khách hàng":"","Tên khách hàng":"(Ký, họ tên)","Địa chỉ khách hàng":"","Kỳ-tháng/năm":"","Loại hóa đơn":"(Ký, họ tên)","Ngày phát hành":"","Tổng tiền":"0","Số điện thoại":"","Thu ngân viên":"(Ký, họ tên)","Số CTơ":"","Số Cột":"","Tên Trạm":""},{"Mã Sổ GCS":2320,"ID hóa đơn":1777561461.0,"Mã khách hàng":"PA09020215103","Tên khách hàng":"Lưu Thị Hồng","Địa chỉ khách hàng":"Thôn Thái Hạc, xã Thư Vũ, tỉnh Hưng Yên","Kỳ-tháng/năm":"1-5/2026","Loại hóa đơn":"TD","Ngày phát hành":"02-06-2026 00:00:00","Tổng tiền":"10.714","Số điện thoại":979235010.0,"Thu ngân viên":"Thu Việt Thuận","Số CTơ":20584745.0,"Số Cột":"1.10","Tên Trạm":"TBA Thái Hạc"},{"Mã Sổ GCS":2320,"ID hóa đơn":1777561473.0,"Mã khách hàng":"PA09020214909","Tên khách hàng":"Phạm Văn Đạt","Địa chỉ khách hàng":"Thôn Thái Hạc, xã Thư Vũ, tỉnh Hưng Yên","Kỳ-tháng/năm":"1-5/2026","Loại hóa đơn":"TD","Ngày phát hành":"02-06-2026 00:00:00","Tổng tiền":"1.489.298","Số điện thoại":976303789.0,"Thu ngân viên":"Thu Việt Thuận","Số CTơ":20587124.0,"Số Cột":"1.4/1.8","Tên Trạm":"TBA Thái Hạc"},{"Mã Sổ GCS":2320,"ID hóa đơn":1777561304.0,"Mã khách hàng":"PA09020219030","Tên khách hàng":"Phạm Văn Tân","Địa chỉ khách hàng":"Thôn Thái Hạc, xã Thư Vũ, tỉnh Hưng Yên","Kỳ-tháng/năm":"1-5/2026","Loại hóa đơn":"TD","Ngày phát hành":"02-06-2026 00:00:00","Tổng tiền":"555.822","Số điện thoại":981971631.0,"Thu ngân viên":"Thu Việt Thuận","Số CTơ":20584807.0,"Số Cột":"1.9/1.4","Tên Trạm":"TBA Thái Hạc"},{"Mã Sổ GCS":2320,"ID hóa đơn":1777561696.0,"Mã khách hàng":"PA09020214266","Tên khách hàng":"Bùi Đình Lào","Địa chỉ khách hàng":"Thôn Thái Hạc, xã Thư Vũ, tỉnh Hưng Yên","Kỳ-tháng/năm":"1-5/2026","Loại hóa đơn":"TD","Ngày phát hành":"02-06-2026 00:00:00","Tổng tiền":"204.552","Số điện thoại":327234828.0,"Thu ngân viên":"Thu Việt Thuận","Số CTơ":20586328.0,"Số Cột":"2.25/1.2","Tên Trạm":"TBA Thái Hạc"},{"Mã Sổ GCS":2323,"ID hóa đơn":1777553463.0,"Mã khách hàng":"PA09020218731","Tên khách hàng":"Nguyễn Thế Hưng","Địa chỉ khách hàng":"Thôn Bình Chính, xã Thư Vũ, tỉnh Hưng Yên","Kỳ-tháng/năm":"1-5/2026","Loại hóa đơn":"TD","Ngày phát hành":"02-06-2026 00:00:00","Tổng tiền":"444.031","Số điện thoại":382506536.0,"Thu ngân viên":"Thu Việt Thuận","Số CTơ":20592005.0,"Số Cột":"2.14/1.5/1.1","Tên Trạm":"TBA BÌNH CHÍNH 2 VIỆT THUẬN"},{"Mã Sổ GCS":2324,"ID hóa đơn":1777556141.0,"Mã khách hàng":"PA09020318550","Tên khách hàng":"Nguyễn Thị Thìn","Địa chỉ khách hàng":"Thôn Bình Chính, xã Thư Vũ, tỉnh Hưng Yên","Kỳ-tháng/năm":"1-5/2026","Loại hóa đơn":"TD","Ngày phát hành":"02-06-2026 00:00:00","Tổng tiền":"47.140","Số điện thoại":901531970.0,"Thu ngân viên":"Thu Việt Thuận","Số CTơ":20586371.0,"Số Cột":"1.2/1.2/1.1","Tên Trạm":"TBA Bình Chính Việt Thuận"},{"Mã Sổ GCS":2324,"ID hóa đơn":1777556288.0,"Mã khách hàng":"PA09020218633","Tên khách hàng":"Bùi Duy Đồng","Địa chỉ khách hàng":"Thôn Bình Chính, xã Thư Vũ, tỉnh Hưng Yên","Kỳ-tháng/năm":"1-5/2026","Loại hóa đơn":"TD","Ngày phát hành":"02-06-2026 00:00:00","Tổng tiền":"669.146","Số điện thoại":362366302.0,"Thu ngân viên":"Thu Việt Thuận","Số CTơ":20590653.0,"Số Cột":"1.2/1.2/1.7","Tên Trạm":"TBA Bình Chính Việt Thuận"},{"Mã Sổ GCS":2325,"ID hóa đơn":1777560908.0,"Mã khách hàng":"PA09020339758","Tên khách hàng":"CÔNG TY TNHH XÂY DỰNG ÁNH SƠN","Địa chỉ khách hàng":"Số nhà 556, đường Lê Quý Đôn, tổ 12,  Phường Trần Lãm, Tỉnh Hưng Yên, Việt Nam","Kỳ-tháng/năm":"1-5/2026","Loại hóa đơn":"TD","Ngày phát hành":"02-06-2026 00:00:00","Tổng tiền":"379.835","Số điện thoại":382828627.0,"Thu ngân viên":"Thu Việt Thuận","Số CTơ":2510002460.0,"Số Cột":"1.10","Tên Trạm":"TBA Hợp Long Vũ Việt"},{"Mã Sổ GCS":2325,"ID hóa đơn":1777560765.0,"Mã khách hàng":"PA09020215835","Tên khách hàng":"Lê Văn Phúc","Địa chỉ khách hàng":"Thôn Hợp Long, xã Thư Vũ, tỉnh Hưng Yên","Kỳ-tháng/năm":"1-5/2026","Loại hóa đơn":"TD","Ngày phát hành":"02-06-2026 00:00:00","Tổng tiền":"25.713","Số điện thoại":705581284.0,"Thu ngân viên":"Thu Việt Thuận","Số CTơ":20576992.0,"Số Cột":"1.10/1.7","Tên Trạm":"TBA Hợp Long Vũ Việt"},{"Mã Sổ GCS":2325,"ID hóa đơn":1777561346.0,"Mã khách hàng":"PA09020334170","Tên khách hàng":"Bùi Thị Hoa","Địa chỉ khách hàng":"Thôn Hợp Long, xã Thư Vũ, tỉnh Hưng Yên","Kỳ-tháng/năm":"1-5/2026","Loại hóa đơn":"TD","Ngày phát hành":"02-06-2026 00:00:00","Tổng tiền":"96.163","Số điện thoại":856182215.0,"Thu ngân viên":"Thu Việt Thuận","Số CTơ":20593448.0,"Số Cột":"3.3/1.5/1.7","Tên Trạm":"TBA Hợp Long Vũ Việt"},{"Mã Sổ GCS":2326,"ID hóa đơn":1777557733.0,"Mã khách hàng":"PA09020217830","Tên khách hàng":"Hội trường thôn Trung Hoà","Địa chỉ khách hàng":"Thôn Hợp Long, xã Thư Vũ, tỉnh Hưng Yên","Kỳ-tháng/năm":"1-5/2026","Loại hóa đơn":"TD","Ngày phát hành":"02-06-2026 00:00:00","Tổng tiền":"64.910","Số điện thoại":989732730.0,"Thu ngân viên":"Thu Việt Thuận","Số CTơ":20510011.0,"Số Cột":"(1.2).1","Tên Trạm":"TBA Trung Hòa Việt Thuận -RD"},{"Mã Sổ GCS":2328,"ID hóa đơn":1777560152.0,"Mã khách hàng":"PA09020214369","Tên khách hàng":"Lưu Thị Chính","Địa chỉ khách hàng":"Thôn Việt Tiến, xã Thư Vũ, tỉnh Hưng Yên","Kỳ-tháng/năm":"1-5/2026","Loại hóa đơn":"TD","Ngày phát hành":"02-06-2026 00:00:00","Tổng tiền":"617.341","Số điện thoại":335694338.0,"Thu ngân viên":"Thu Việt Thuận","Số CTơ":20518219.0,"Số Cột":"2.7","Tên Trạm":"TBA Việt Tiến Vũ Việt"},{"Mã Sổ GCS":2328,"ID hóa đơn":1777560964.0,"Mã khách hàng":"PA09020214666","Tên khách hàng":"Bùi Thị Ruyến","Địa chỉ khách hàng":"Thôn Việt Tiến, xã Thư Vũ, tỉnh Hưng Yên","Kỳ-tháng/năm":"1-5/2026","Loại hóa đơn":"TD","Ngày phát hành":"02-06-2026 00:00:00","Tổng tiền":"217.836","Số điện thoại":362821139.0,"Thu ngân viên":"Thu Việt Thuận","Số CTơ":20523964.0,"Số Cột":"2.8","Tên Trạm":"TBA Việt Tiến Vũ Việt"},{"Mã Sổ GCS":2328,"ID hóa đơn":1777560814.0,"Mã khách hàng":"PA09020214447","Tên khách hàng":"Nguyễn Thị Dâu","Địa chỉ khách hàng":"Thôn Việt Tiến, xã Thư Vũ, tỉnh Hưng Yên","Kỳ-tháng/năm":"1-5/2026","Loại hóa đơn":"TD","Ngày phát hành":"02-06-2026 00:00:00","Tổng tiền":"211.194","Số điện thoại":374558898.0,"Thu ngân viên":"Thu Việt Thuận","Số CTơ":20525906.0,"Số Cột":"2.9/2.7/1.6","Tên Trạm":"TBA Việt Tiến Vũ Việt"},{"Mã Sổ GCS":2330,"ID hóa đơn":1777553285.0,"Mã khách hàng":"PA09020215130","Tên khách hàng":"PHẠM TUẤN VIỆT","Địa chỉ khách hàng":"Thôn Đồng Tiến, xã Thư Vũ, tỉnh Hưng Yên","Kỳ-tháng/năm":"1-5/2026","Loại hóa đơn":"TD","Ngày phát hành":"02-06-2026 00:00:00","Tổng tiền":"582.185","Số điện thoại":375236569.0,"Thu ngân viên":"Thu Việt Thuận","Số CTơ":20572634.0,"Số Cột":"1.10","Tên Trạm":"TBA ĐỒNG TIẾN 2"},{"Mã Sổ GCS":2331,"ID hóa đơn":1777559160.0,"Mã khách hàng":"PA09020217877","Tên khách hàng":"Nguyễn Văn Cầu","Địa chỉ khách hàng":"Thôn Việt Thắng, xã Thư Vũ, tỉnh Hưng Yên","Kỳ-tháng/năm":"1-5/2026","Loại hóa đơn":"TD","Ngày phát hành":"02-06-2026 00:00:00","Tổng tiền":"250.024","Số điện thoại":916341015.0,"Thu ngân viên":"Thu Việt Thuận","Số CTơ":20588397.0,"Số Cột":"1.6/1.10/1.1","Tên Trạm":"TBA Việt Thắng Vũ Việt"},{"Mã Sổ GCS":2331,"ID hóa đơn":1777559768.0,"Mã khách hàng":"PA09020307517","Tên khách hàng":"Nguyễn Văn Cầu","Địa chỉ khách hàng":"Thôn Việt Cường, xã Thư Vũ, tỉnh Hưng Yên","Kỳ-tháng/năm":"1-5/2026","Loại hóa đơn":"TD","Ngày phát hành":"02-06-2026 00:00:00","Tổng tiền":"459.454","Số điện thoại":916341015.0,"Thu ngân viên":"Thu Việt Thuận","Số CTơ":20592742.0,"Số Cột":"1.6/1.9","Tên Trạm":"TBA Việt Thắng Vũ Việt"},{"Mã Sổ GCS":2331,"ID hóa đơn":1777559916.0,"Mã khách hàng":"PA09020214014","Tên khách hàng":"Đỗ Văn Thiêm","Địa chỉ khách hàng":"Thôn Việt Cường, xã Thư Vũ, tỉnh Hưng Yên","Kỳ-tháng/năm":"1-5/2026","Loại hóa đơn":"TD","Ngày phát hành":"02-06-2026 00:00:00","Tổng tiền":"151.416","Số điện thoại":988351954.0,"Thu ngân viên":"Thu Việt Thuận","Số CTơ":20573429.0,"Số Cột":"2.1/1.5/1.1","Tên Trạm":"TBA Việt Thắng Vũ Việt"},{"Mã Sổ GCS":2331,"ID hóa đơn":1777558949.0,"Mã khách hàng":"PA09020302440","Tên khách hàng":"Đỗ Văn Chính","Địa chỉ khách hàng":"Thôn Việt Cường, xã Thư Vũ, tỉnh Hưng Yên","Kỳ-tháng/năm":"1-5/2026","Loại hóa đơn":"TD","Ngày phát hành":"02-06-2026 00:00:00","Tổng tiền":"366.919","Số điện thoại":942193764.0,"Thu ngân viên":"Thu Việt Thuận","Số CTơ":20590912.0,"Số Cột":"2.1/1.5/1.1","Tên Trạm":"TBA Việt Thắng Vũ Việt"},{"Mã Sổ GCS":2332,"ID hóa đơn":1777558890.0,"Mã khách hàng":"PA09020332416","Tên khách hàng":"Đỗ Văn Năm","Địa chỉ khách hàng":"Thôn Đồng Tiến, xã Thư Vũ, tỉnh Hưng Yên","Kỳ-tháng/năm":"1-5/2026","Loại hóa đơn":"TD","Ngày phát hành":"02-06-2026 00:00:00","Tổng tiền":"418.310","Số điện thoại":934211034.0,"Thu ngân viên":"Thu Việt Thuận","Số CTơ":20577442.0,"Số Cột":"1.4","Tên Trạm":"TBA Đồng Tiến - Việt Thuận"},{"Mã Sổ GCS":2332,"ID hóa đơn":1777558337.0,"Mã khách hàng":"PA09020323499","Tên khách hàng":"Đỗ Văn Dũng","Địa chỉ khách hàng":"Thôn Việt Cường, xã Thư Vũ, tỉnh Hưng Yên","Kỳ-tháng/năm":"1-5/2026","Loại hóa đơn":"TD","Ngày phát hành":"02-06-2026 00:00:00","Tổng tiền":"173.094","Số điện thoại":796187969.0,"Thu ngân viên":"Thu Việt Thuận","Số CTơ":20591403.0,"Số Cột":"2.14","Tên Trạm":"TBA Đồng Tiến - Việt Thuận"},{"Mã Sổ GCS":2333,"ID hóa đơn":1777553871.0,"Mã khách hàng":"PA09020213830","Tên khách hàng":"Lê Thị Cương","Địa chỉ khách hàng":"Thôn Việt Hùng, xã Thư Vũ, tỉnh Hưng Yên","Kỳ-tháng/năm":"1-5/2026","Loại hóa đơn":"TD","Ngày phát hành":"02-06-2026 00:00:00","Tổng tiền":"98.565","Số điện thoại":389847333.0,"Thu ngân viên":"Thu Việt Thuận","Số CTơ":20590152.0,"Số Cột":"2.9/1.1","Tên Trạm":"TBA ÁNH SÁNG VŨ VIỆT"},{"Mã Sổ GCS":2333,"ID hóa đơn":1777554072.0,"Mã khách hàng":"PA09020246039","Tên khách hàng":"Lê Thanh Tùng","Địa chỉ khách hàng":"Thôn Việt Hùng, xã Thư Vũ, tỉnh Hưng Yên","Kỳ-tháng/năm":"1-5/2026","Loại hóa đơn":"TD","Ngày phát hành":"02-06-2026 00:00:00","Tổng tiền":"640.006","Số điện thoại":389847333.0,"Thu ngân viên":"Thu Việt Thuận","Số CTơ":20587344.0,"Số Cột":"2.9/1.1","Tên Trạm":"TBA ÁNH SÁNG VŨ VIỆT"},{"Mã Sổ GCS":2336,"ID hóa đơn":1777559135.0,"Mã khách hàng":"PA09020216899","Tên khách hàng":"Bùi Thị Hợi","Địa chỉ khách hàng":"Thôn Hợp Long, xã Thư Vũ, tỉnh Hưng Yên","Kỳ-tháng/năm":"1-5/2026","Loại hóa đơn":"TD","Ngày phát hành":"02-06-2026 00:00:00","Tổng tiền":"17.142","Số điện thoại":976844160.0,"Thu ngân viên":"Thu Việt Thuận","Số CTơ":20585251.0,"Số Cột":"1.8/1.1","Tên Trạm":"TBA HỢP LONG 3 XÃ VIỆT THUẬN"},{"Mã Sổ GCS":2336,"ID hóa đơn":1777559991.0,"Mã khách hàng":"PA09020215862","Tên khách hàng":"Bùi Công Hoàng","Địa chỉ khách hàng":"Thôn Hợp Long, xã Thư Vũ, tỉnh Hưng Yên","Kỳ-tháng/năm":"1-5/2026","Loại hóa đơn":"TD","Ngày phát hành":"02-06-2026 00:00:00","Tổng tiền":"140.346","Số điện thoại":967658126.0,"Thu ngân viên":"Thu Việt Thuận","Số CTơ":20530143.0,"Số Cột":"1.9/1.4","Tên Trạm":"TBA HỢP LONG 3 XÃ VIỆT THUẬN"},{"Mã Sổ GCS":2336,"ID hóa đơn":1777560027.0,"Mã khách hàng":"PA09020302072","Tên khách hàng":"Vũ Văn Trường","Địa chỉ khách hàng":"Thôn Đồng Tiến, xã Thư Vũ, tỉnh Hưng Yên","Kỳ-tháng/năm":"1-5/2026","Loại hóa đơn":"TD","Ngày phát hành":"02-06-2026 00:00:00","Tổng tiền":"415.757","Số điện thoại":702202830.0,"Thu ngân viên":"Thu Việt Thuận","Số CTơ":20584492.0,"Số Cột":"2.12","Tên Trạm":"TBA HỢP LONG 3 XÃ VIỆT THUẬN"},{"Mã Sổ GCS":2336,"ID hóa đơn":1777559879.0,"Mã khách hàng":"PA09020215330","Tên khách hàng":"Vũ Văn Hà","Địa chỉ khách hàng":"Thôn Việt Thắng, xã Thư Vũ, tỉnh Hưng Yên","Kỳ-tháng/năm":"1-5/2026","Loại hóa đơn":"TD","Ngày phát hành":"02-06-2026 00:00:00","Tổng tiền":"341.215","Số điện thoại":702202830.0,"Thu ngân viên":"Thu Việt Thuận","Số CTơ":20503695.0,"Số Cột":"2.12","Tên Trạm":"TBA HỢP LONG 3 XÃ VIỆT THUẬN"},{"Mã Sổ GCS":2337,"ID hóa đơn":1777555042.0,"Mã khách hàng":"PA09020214439","Tên khách hàng":"Bùi Văn Tiến","Địa chỉ khách hàng":"Thôn Việt Tiến, xã Thư Vũ, tỉnh Hưng Yên","Kỳ-tháng/năm":"1-5/2026","Loại hóa đơn":"TD","Ngày phát hành":"02-06-2026 00:00:00","Tổng tiền":"197.910","Số điện thoại":985704306.0,"Thu ngân viên":"Thu Việt Thuận","Số CTơ":20590636.0,"Số Cột":"2.7/1.6/2.1","Tên Trạm":"TBA Việt Tiến 3 xã Việt Thuận"},{"Mã Sổ GCS":"","ID hóa đơn":"","Mã khách hàng":"","Tên khách hàng":"","Địa chỉ khách hàng":"","Kỳ-tháng/năm":"Số hóa đơn: 28 HĐ","Loại hóa đơn":"","Ngày phát hành":"","Tổng tiền":"9.286.038","Số điện thoại":"","Thu ngân viên":"","Số CTơ":"","Số Cột":"","Tên Trạm":""},{"Mã Sổ GCS":"","ID hóa đơn":"","Mã khách hàng":"","Tên khách hàng":"Thu ngân viên","Địa chỉ khách hàng":"","Kỳ-tháng/năm":"","Loại hóa đơn":"Kế toán","Ngày phát hành":"","Tổng tiền":"0","Số điện thoại":"","Thu ngân viên":"Phòng kinh doanh","Số CTơ":"","Số Cột":"","Tên Trạm":""},{"Mã Sổ GCS":"","ID hóa đơn":"","Mã khách hàng":"","Tên khách hàng":"(Ký, họ tên)","Địa chỉ khách hàng":"","Kỳ-tháng/năm":"","Loại hóa đơn":"(Ký, họ tên)","Ngày phát hành":"","Tổng tiền":"0","Số điện thoại":"","Thu ngân viên":"(Ký, họ tên)","Số CTơ":"","Số Cột":"","Tên Trạm":""},{"Mã Sổ GCS":2870,"ID hóa đơn":1777367618.0,"Mã khách hàng":"PA09020309138","Tên khách hàng":"TRƯỜNG TIỂU HỌC VÀ TRUNG HỌC CƠ SỞ VŨ ĐOÀI","Địa chỉ khách hàng":"Thôn 4, Xã Vũ Tiên, Tỉnh Hưng Yên, Việt Nam","Kỳ-tháng/năm":"1-5/2026","Loại hóa đơn":"TD","Ngày phát hành":"02-06-2026 00:00:00","Tổng tiền":"3.508.808","Số điện thoại":914347856.0,"Thu ngân viên":"Thu Vũ Đoài","Số CTơ":21117474.0,"Số Cột":1.7,"Tên Trạm":"TBA CHĂN NUÔI VŨ ĐOÀI"},{"Mã Sổ GCS":2870,"ID hóa đơn":1777367394.0,"Mã khách hàng":"PA09020315634","Tên khách hàng":"TRƯỜNG TIỂU HỌC VÀ TRUNG HỌC CƠ SỞ VŨ ĐOÀI","Địa chỉ khách hàng":"Thôn 4, Xã Vũ Tiên, Tỉnh Hưng Yên, Việt Nam","Kỳ-tháng/năm":"1-5/2026","Loại hóa đơn":"TD","Ngày phát hành":"02-06-2026 00:00:00","Tổng tiền":"2.944.892","Số điện thoại":914347856.0,"Thu ngân viên":"Thu Vũ Đoài","Số CTơ":21117191.0,"Số Cột":1.8,"Tên Trạm":"TBA CHĂN NUÔI VŨ ĐOÀI"},{"Mã Sổ GCS":"","ID hóa đơn":"","Mã khách hàng":"","Tên khách hàng":"","Địa chỉ khách hàng":"","Kỳ-tháng/năm":"Số hóa đơn: 2 HĐ","Loại hóa đơn":"","Ngày phát hành":"","Tổng tiền":"6.453.700","Số điện thoại":"","Thu ngân viên":"","Số CTơ":"","Số Cột":"","Tên Trạm":""},{"Mã Sổ GCS":"","ID hóa đơn":"","Mã khách hàng":"","Tên khách hàng":"Thu ngân viên","Địa chỉ khách hàng":"","Kỳ-tháng/năm":"","Loại hóa đơn":"Kế toán","Ngày phát hành":"","Tổng tiền":"0","Số điện thoại":"","Thu ngân viên":"Phòng kinh doanh","Số CTơ":"","Số Cột":"","Tên Trạm":""},{"Mã Sổ GCS":"","ID hóa đơn":"","Mã khách hàng":"","Tên khách hàng":"(Ký, họ tên)","Địa chỉ khách hàng":"","Kỳ-tháng/năm":"","Loại hóa đơn":"(Ký, họ tên)","Ngày phát hành":"","Tổng tiền":"0","Số điện thoại":"","Thu ngân viên":"(Ký, họ tên)","Số CTơ":"","Số Cột":"","Tên Trạm":""},{"Mã Sổ GCS":2837,"ID hóa đơn":1776874231.0,"Mã khách hàng":"PA09020315521","Tên khách hàng":"Phạm Thị Thủy","Địa chỉ khách hàng":"Thôn Song Thủy, xã Vũ Tiên, tỉnh Hưng Yên","Kỳ-tháng/năm":"1-5/2026","Loại hóa đơn":"TD","Ngày phát hành":"02-06-2026 00:00:00","Tổng tiền":"555.822","Số điện thoại":923655555.0,"Thu ngân viên":"Thu Vũ Tiến","Số CTơ":2111246351.0,"Số Cột":"2.9/1.1","Tên Trạm":"TBA BƠM THỦY TIÊN"},{"Mã Sổ GCS":2840,"ID hóa đơn":1776878231.0,"Mã khách hàng":"PA09020316280","Tên khách hàng":"Trần Công Trưởng","Địa chỉ khách hàng":"Thôn Lục Tiên, xã Vũ Tiên, tỉnh Hưng Yên","Kỳ-tháng/năm":"1-5/2026","Loại hóa đơn":"TD","Ngày phát hành":"02-06-2026 00:00:00","Tổng tiền":"972.324","Số điện thoại":364111081.0,"Thu ngân viên":"Thu Vũ Tiến","Số CTơ":2111382392.0,"Số Cột":"1.5/1.7/1.6","Tên Trạm":"TBA LỤC TIÊN"},{"Mã Sổ GCS":"","ID hóa đơn":"","Mã khách hàng":"","Tên khách hàng":"","Địa chỉ khách hàng":"","Kỳ-tháng/năm":"Số hóa đơn: 2 HĐ","Loại hóa đơn":"","Ngày phát hành":"","Tổng tiền":"1.528.146","Số điện thoại":"","Thu ngân viên":"","Số CTơ":"","Số Cột":"","Tên Trạm":""},{"Mã Sổ GCS":"","ID hóa đơn":"","Mã khách hàng":"","Tên khách hàng":"Thu ngân viên","Địa chỉ khách hàng":"","Kỳ-tháng/năm":"","Loại hóa đơn":"Kế toán","Ngày phát hành":"","Tổng tiền":"0","Số điện thoại":"","Thu ngân viên":"Phòng kinh doanh","Số CTơ":"","Số Cột":"","Tên Trạm":""},{"Mã Sổ GCS":"","ID hóa đơn":"","Mã khách hàng":"","Tên khách hàng":"(Ký, họ tên)","Địa chỉ khách hàng":"","Kỳ-tháng/năm":"","Loại hóa đơn":"(Ký, họ tên)","Ngày phát hành":"","Tổng tiền":"0","Số điện thoại":"","Thu ngân viên":"(Ký, họ tên)","Số CTơ":"","Số Cột":"","Tên Trạm":""},{"Mã Sổ GCS":2282,"ID hóa đơn":1775574259.0,"Mã khách hàng":"PA09020304240","Tên khách hàng":"Phạm Văn Quynh","Địa chỉ khách hàng":"Thôn Hương, xã Vạn Xuân, tỉnh Hưng Yên","Kỳ-tháng/năm":"1-5/2026","Loại hóa đơn":"TD","Ngày phát hành":"02-06-2026 00:00:00","Tổng tiền":"8.571","Số điện thoại":386107091.0,"Thu ngân viên":"Thu Xuân Hòa","Số CTơ":2210601836.0,"Số Cột":1.13,"Tên Trạm":"Trạm Quang Lê Xuân Hòa - RD"},{"Mã Sổ GCS":"","ID hóa đơn":"","Mã khách hàng":"","Tên khách hàng":"","Địa chỉ khách hàng":"","Kỳ-tháng/năm":"Số hóa đơn: 1 HĐ","Loại hóa đơn":"","Ngày phát hành":"","Tổng tiền":"8.571","Số điện thoại":"","Thu ngân viên":"","Số CTơ":"","Số Cột":"","Tên Trạm":""},{"Mã Sổ GCS":"","ID hóa đơn":"","Mã khách hàng":"","Tên khách hàng":"Thu ngân viên","Địa chỉ khách hàng":"","Kỳ-tháng/năm":"","Loại hóa đơn":"Kế toán","Ngày phát hành":"","Tổng tiền":"0","Số điện thoại":"","Thu ngân viên":"Phòng kinh doanh","Số CTơ":"","Số Cột":"","Tên Trạm":""},{"Mã Sổ GCS":"","ID hóa đơn":"","Mã khách hàng":"","Tên khách hàng":"(Ký, họ tên)","Địa chỉ khách hàng":"","Kỳ-tháng/năm":"","Loại hóa đơn":"(Ký, họ tên)","Ngày phát hành":"","Tổng tiền":"0","Số điện thoại":"","Thu ngân viên":"(Ký, họ tên)","Số CTơ":"","Số Cột":"","Tên Trạm":""}]}